{"attributes": {"評価値計算時の重み付加": "無"}, "sequence": [{"OwnSpeed": 93.9, "StrDeg": 1.5, "inf_DP": 5.7485349999999995, "Distance_ref": 54.65, "TgtSpeed_ref": 87.12, "TgtXPos_LeftUp": 452.0, "TgtYPos_LeftUp": 42.0, "TgtWidth": 72.0, "TgtHeight": 112.0}, {"OwnSpeed": 94.1, "StrDeg": 1.6, "inf_DP": 5.7485349999999995, "Distance_ref": 54.45, "TgtSpeed_ref": 87.1, "TgtXPos_LeftUp": 451.0, "TgtYPos_LeftUp": 42.0, "TgtWidth": 72.0, "TgtHeight": 112.0}, {"OwnSpeed": 94.3, "StrDeg": 1.6, "inf_DP": 5.7485349999999995, "Distance_ref": 54.26, "TgtSpeed_ref": 87.08, "TgtXPos_LeftUp": 449.0, "TgtYPos_LeftUp": 42.0, "TgtWidth": 73.0, "TgtHeight": 112.0}, {"OwnSpeed": 94.4, "StrDeg": 1.6, "inf_DP": 5.7485349999999995, "Distance_ref": 54.07, "TgtSpeed_ref": 87.11, "TgtXPos_LeftUp": 448.0, "TgtYPos_LeftUp": 43.0, "TgtWidth": 73.0, "TgtHeight": 112.0}, {"OwnSpeed": 94.5, "StrDeg": 1.6, "inf_DP": 5.748779, "Distance_ref": 53.86, "TgtSpeed_ref": 87.14, "TgtXPos_LeftUp": 446.0, "TgtYPos_LeftUp": 43.0, "TgtWidth": 74.0, "TgtHeight": 113.0}, {"OwnSpeed": 94.7, "StrDeg": 1.6, "inf_DP": 5.748779, "Distance_ref": 53.66, "TgtSpeed_ref": 87.11, "TgtXPos_LeftUp": 444.0, "TgtYPos_LeftUp": 42.0, "TgtWidth": 74.0, "TgtHeight": 113.0}, {"OwnSpeed": 94.8, "StrDeg": 1.6, "inf_DP": 5.749023, "Distance_ref": 53.45, "TgtSpeed_ref": 87.18, "TgtXPos_LeftUp": 442.0, "TgtYPos_LeftUp": 42.0, "TgtWidth": 75.0, "TgtHeight": 114.0}, {"OwnSpeed": 95.0, "StrDeg": 1.6, "inf_DP": 5.749268, "Distance_ref": 53.23, "TgtSpeed_ref": 87.24, "TgtXPos_LeftUp": 440.0, "TgtYPos_LeftUp": 43.0, "TgtWidth": 75.0, "TgtHeight": 114.0}, {"OwnSpeed": 95.2, "StrDeg": 1.6, "inf_DP": 5.749268, "Distance_ref": 53.0, "TgtSpeed_ref": 87.28, "TgtXPos_LeftUp": 438.0, "TgtYPos_LeftUp": 43.0, "TgtWidth": 75.0, "TgtHeight": 114.0}, {"OwnSpeed": 95.3, "StrDeg": 1.2, "inf_DP": 5.749268, "Distance_ref": 52.76, "TgtSpeed_ref": 87.32, "TgtXPos_LeftUp": 437.0, "TgtYPos_LeftUp": 41.0, "TgtWidth": 75.0, "TgtHeight": 115.0}, {"OwnSpeed": 95.3, "StrDeg": 0.7, "inf_DP": 5.749268, "Distance_ref": 52.54, "TgtSpeed_ref": 87.26, "TgtXPos_LeftUp": 436.0, "TgtYPos_LeftUp": 40.0, "TgtWidth": 76.0, "TgtHeight": 115.0}, {"OwnSpeed": 95.3, "StrDeg": 0.0, "inf_DP": 5.749268, "Distance_ref": 52.32, "TgtSpeed_ref": 87.21, "TgtXPos_LeftUp": 436.0, "TgtYPos_LeftUp": 40.0, "TgtWidth": 76.0, "TgtHeight": 115.0}, {"OwnSpeed": 95.3, "StrDeg": -0.5, "inf_DP": 5.749023, "Distance_ref": 52.1, "TgtSpeed_ref": 87.23, "TgtXPos_LeftUp": 436.0, "TgtYPos_LeftUp": 39.0, "TgtWidth": 77.0, "TgtHeight": 116.0}, {"OwnSpeed": 95.2, "StrDeg": -0.5, "inf_DP": 5.749268, "Distance_ref": 51.89, "TgtSpeed_ref": 87.17, "TgtXPos_LeftUp": 437.0, "TgtYPos_LeftUp": 37.0, "TgtWidth": 77.0, "TgtHeight": 116.0}, {"OwnSpeed": 95.0, "StrDeg": -0.6, "inf_DP": 5.749268, "Distance_ref": 51.68, "TgtSpeed_ref": 87.17, "TgtXPos_LeftUp": 438.0, "TgtYPos_LeftUp": 36.0, "TgtWidth": 77.0, "TgtHeight": 117.0}, {"OwnSpeed": 94.9, "StrDeg": -0.6, "inf_DP": 5.749268, "Distance_ref": 51.48, "TgtSpeed_ref": 87.15, "TgtXPos_LeftUp": 439.0, "TgtYPos_LeftUp": 36.0, "TgtWidth": 78.0, "TgtHeight": 117.0}, {"OwnSpeed": 94.7, "StrDeg": -0.8, "inf_DP": 5.749268, "Distance_ref": 51.28, "TgtSpeed_ref": 87.11, "TgtXPos_LeftUp": 441.0, "TgtYPos_LeftUp": 34.0, "TgtWidth": 78.0, "TgtHeight": 118.0}, {"OwnSpeed": 94.5, "StrDeg": -0.7, "inf_DP": 5.749268, "Distance_ref": 51.06, "TgtSpeed_ref": 87.12, "TgtXPos_LeftUp": 442.0, "TgtYPos_LeftUp": 33.0, "TgtWidth": 79.0, "TgtHeight": 118.0}, {"OwnSpeed": 94.4, "StrDeg": -0.7, "inf_DP": 5.749268, "Distance_ref": 50.85, "TgtSpeed_ref": 87.09, "TgtXPos_LeftUp": 444.0, "TgtYPos_LeftUp": 34.0, "TgtWidth": 79.0, "TgtHeight": 119.0}, {"OwnSpeed": 94.3, "StrDeg": -0.7, "inf_DP": 5.749268, "Distance_ref": 50.65, "TgtSpeed_ref": 87.0, "TgtXPos_LeftUp": 446.0, "TgtYPos_LeftUp": 33.0, "TgtWidth": 79.0, "TgtHeight": 120.0}, {"OwnSpeed": 94.0, "StrDeg": -0.7, "inf_DP": 5.749268, "Distance_ref": 50.45, "TgtSpeed_ref": 86.95, "TgtXPos_LeftUp": 447.0, "TgtYPos_LeftUp": 31.0, "TgtWidth": 79.0, "TgtHeight": 120.0}, {"OwnSpeed": 93.9, "StrDeg": -0.7, "inf_DP": 5.749512, "Distance_ref": 50.26, "TgtSpeed_ref": 86.85, "TgtXPos_LeftUp": 448.0, "TgtYPos_LeftUp": 30.0, "TgtWidth": 80.0, "TgtHeight": 121.0}, {"OwnSpeed": 93.8, "StrDeg": -0.6, "inf_DP": 5.749512, "Distance_ref": 50.06, "TgtSpeed_ref": 86.82, "TgtXPos_LeftUp": 449.0, "TgtYPos_LeftUp": 31.0, "TgtWidth": 80.0, "TgtHeight": 121.0}, {"OwnSpeed": 93.6, "StrDeg": -0.5, "inf_DP": 5.749268, "Distance_ref": 49.86, "TgtSpeed_ref": 86.8, "TgtXPos_LeftUp": 450.0, "TgtYPos_LeftUp": 32.0, "TgtWidth": 80.0, "TgtHeight": 121.0}, {"OwnSpeed": 93.5, "StrDeg": 0.2, "inf_DP": 5.749268, "Distance_ref": 49.68, "TgtSpeed_ref": 86.73, "TgtXPos_LeftUp": 451.0, "TgtYPos_LeftUp": 33.0, "TgtWidth": 80.0, "TgtHeight": 121.0}, {"OwnSpeed": 93.5, "StrDeg": 0.4, "inf_DP": 5.749268, "Distance_ref": 49.49, "TgtSpeed_ref": 86.74, "TgtXPos_LeftUp": 451.0, "TgtYPos_LeftUp": 32.0, "TgtWidth": 81.0, "TgtHeight": 122.0}, {"OwnSpeed": 93.4, "StrDeg": 0.5, "inf_DP": 5.749268, "Distance_ref": 49.29, "TgtSpeed_ref": 86.78, "TgtXPos_LeftUp": 451.0, "TgtYPos_LeftUp": 33.0, "TgtWidth": 81.0, "TgtHeight": 123.0}, {"OwnSpeed": 93.3, "StrDeg": 0.5, "inf_DP": 5.749268, "Distance_ref": 49.11, "TgtSpeed_ref": 86.82, "TgtXPos_LeftUp": 450.0, "TgtYPos_LeftUp": 34.0, "TgtWidth": 82.0, "TgtHeight": 123.0}, {"OwnSpeed": 93.2, "StrDeg": 0.6, "inf_DP": 5.749268, "Distance_ref": 48.91, "TgtSpeed_ref": 86.92, "TgtXPos_LeftUp": 449.0, "TgtYPos_LeftUp": 32.0, "TgtWidth": 82.0, "TgtHeight": 123.0}, {"OwnSpeed": 93.2, "StrDeg": 0.5, "inf_DP": 5.749268, "Distance_ref": 48.74, "TgtSpeed_ref": 86.9, "TgtXPos_LeftUp": 448.0, "TgtYPos_LeftUp": 30.0, "TgtWidth": 83.0, "TgtHeight": 124.0}, {"OwnSpeed": 93.1, "StrDeg": 0.6, "inf_DP": 5.749268, "Distance_ref": 48.58, "TgtSpeed_ref": 86.89, "TgtXPos_LeftUp": 448.0, "TgtYPos_LeftUp": 31.0, "TgtWidth": 82.0, "TgtHeight": 125.0}, {"OwnSpeed": 93.1, "StrDeg": 0.5, "inf_DP": 5.749512, "Distance_ref": 48.39, "TgtSpeed_ref": 86.96, "TgtXPos_LeftUp": 448.0, "TgtYPos_LeftUp": 32.0, "TgtWidth": 82.0, "TgtHeight": 125.0}, {"OwnSpeed": 93.1, "StrDeg": 0.5, "inf_DP": 5.749512, "Distance_ref": 48.22, "TgtSpeed_ref": 86.99, "TgtXPos_LeftUp": 447.0, "TgtYPos_LeftUp": 30.0, "TgtWidth": 83.0, "TgtHeight": 126.0}, {"OwnSpeed": 93.0, "StrDeg": 0.5, "inf_DP": 5.749512, "Distance_ref": 48.06, "TgtSpeed_ref": 86.98, "TgtXPos_LeftUp": 445.0, "TgtYPos_LeftUp": 29.0, "TgtWidth": 84.0, "TgtHeight": 127.0}, {"OwnSpeed": 92.9, "StrDeg": 0.5, "inf_DP": 5.749512, "Distance_ref": 47.92, "TgtSpeed_ref": 86.97, "TgtXPos_LeftUp": 444.0, "TgtYPos_LeftUp": 31.0, "TgtWidth": 85.0, "TgtHeight": 127.0}, {"OwnSpeed": 92.8, "StrDeg": 0.6, "inf_DP": 5.749512, "Distance_ref": 47.79, "TgtSpeed_ref": 86.92, "TgtXPos_LeftUp": 444.0, "TgtYPos_LeftUp": 29.0, "TgtWidth": 84.0, "TgtHeight": 128.0}, {"OwnSpeed": 92.7, "StrDeg": 0.6, "inf_DP": 5.749756, "Distance_ref": 47.64, "TgtSpeed_ref": 86.98, "TgtXPos_LeftUp": 443.0, "TgtYPos_LeftUp": 27.0, "TgtWidth": 85.0, "TgtHeight": 128.0}, {"OwnSpeed": 92.6, "StrDeg": 0.6, "inf_DP": 5.749756, "Distance_ref": 47.46, "TgtSpeed_ref": 87.0, "TgtXPos_LeftUp": 443.0, "TgtYPos_LeftUp": 27.0, "TgtWidth": 85.0, "TgtHeight": 128.0}, {"OwnSpeed": 92.5, "StrDeg": 0.5, "inf_DP": 5.749756, "Distance_ref": 47.32, "TgtSpeed_ref": 86.94, "TgtXPos_LeftUp": 443.0, "TgtYPos_LeftUp": 28.0, "TgtWidth": 85.0, "TgtHeight": 128.0}, {"OwnSpeed": 92.4, "StrDeg": 0.5, "inf_DP": 5.749756, "Distance_ref": 47.18, "TgtSpeed_ref": 86.94, "TgtXPos_LeftUp": 443.0, "TgtYPos_LeftUp": 28.0, "TgtWidth": 85.0, "TgtHeight": 128.0}, {"OwnSpeed": 92.4, "StrDeg": 0.6, "inf_DP": 5.749756, "Distance_ref": 47.02, "TgtSpeed_ref": 86.98, "TgtXPos_LeftUp": 443.0, "TgtYPos_LeftUp": 28.0, "TgtWidth": 85.0, "TgtHeight": 128.0}, {"OwnSpeed": 92.2, "StrDeg": 0.6, "inf_DP": 5.749756, "Distance_ref": 46.85, "TgtSpeed_ref": 86.98, "TgtXPos_LeftUp": 443.0, "TgtYPos_LeftUp": 27.0, "TgtWidth": 85.0, "TgtHeight": 128.0}, {"OwnSpeed": 92.1, "StrDeg": 0.5, "inf_DP": 5.749756, "Distance_ref": 46.68, "TgtSpeed_ref": 86.94, "TgtXPos_LeftUp": 443.0, "TgtYPos_LeftUp": 27.0, "TgtWidth": 85.0, "TgtHeight": 128.0}, {"OwnSpeed": 92.0, "StrDeg": 0.5, "inf_DP": 5.749756, "Distance_ref": 46.54, "TgtSpeed_ref": 86.87, "TgtXPos_LeftUp": 443.0, "TgtYPos_LeftUp": 27.0, "TgtWidth": 86.0, "TgtHeight": 131.0}, {"OwnSpeed": 91.9, "StrDeg": 0.5, "inf_DP": 5.749756, "Distance_ref": 46.41, "TgtSpeed_ref": 86.87, "TgtXPos_LeftUp": 443.0, "TgtYPos_LeftUp": 26.0, "TgtWidth": 86.0, "TgtHeight": 131.0}, {"OwnSpeed": 91.7, "StrDeg": 0.6, "inf_DP": 5.749756, "Distance_ref": 46.26, "TgtSpeed_ref": 86.93, "TgtXPos_LeftUp": 443.0, "TgtYPos_LeftUp": 23.0, "TgtWidth": 87.0, "TgtHeight": 132.0}, {"OwnSpeed": 91.6, "StrDeg": 0.5, "inf_DP": 5.749023, "Distance_ref": 46.12, "TgtSpeed_ref": 86.92, "TgtXPos_LeftUp": 442.0, "TgtYPos_LeftUp": 22.0, "TgtWidth": 89.0, "TgtHeight": 133.0}, {"OwnSpeed": 91.6, "StrDeg": 0.6, "inf_DP": 5.749023, "Distance_ref": 46.01, "TgtSpeed_ref": 86.88, "TgtXPos_LeftUp": 442.0, "TgtYPos_LeftUp": 23.0, "TgtWidth": 89.0, "TgtHeight": 133.0}, {"OwnSpeed": 91.5, "StrDeg": 0.5, "inf_DP": 5.749023, "Distance_ref": 45.89, "TgtSpeed_ref": 86.86, "TgtXPos_LeftUp": 442.0, "TgtYPos_LeftUp": 23.0, "TgtWidth": 89.0, "TgtHeight": 133.0}, {"OwnSpeed": 91.3, "StrDeg": 0.6, "inf_DP": 5.749023, "Distance_ref": 45.78, "TgtSpeed_ref": 86.91, "TgtXPos_LeftUp": 442.0, "TgtYPos_LeftUp": 24.0, "TgtWidth": 89.0, "TgtHeight": 133.0}, {"OwnSpeed": 91.2, "StrDeg": 0.6, "inf_DP": 5.749023, "Distance_ref": 45.66, "TgtSpeed_ref": 86.96, "TgtXPos_LeftUp": 442.0, "TgtYPos_LeftUp": 25.0, "TgtWidth": 90.0, "TgtHeight": 133.0}, {"OwnSpeed": 91.1, "StrDeg": 0.5, "inf_DP": 5.749023, "Distance_ref": 45.55, "TgtSpeed_ref": 86.95, "TgtXPos_LeftUp": 443.0, "TgtYPos_LeftUp": 26.0, "TgtWidth": 89.0, "TgtHeight": 133.0}, {"OwnSpeed": 91.0, "StrDeg": 0.5, "inf_DP": 5.749023, "Distance_ref": 45.45, "TgtSpeed_ref": 86.89, "TgtXPos_LeftUp": 442.0, "TgtYPos_LeftUp": 26.0, "TgtWidth": 90.0, "TgtHeight": 134.0}, {"OwnSpeed": 90.8, "StrDeg": 0.5, "inf_DP": 5.749023, "Distance_ref": 45.35, "TgtSpeed_ref": 86.88, "TgtXPos_LeftUp": 442.0, "TgtYPos_LeftUp": 25.0, "TgtWidth": 89.0, "TgtHeight": 134.0}, {"OwnSpeed": 90.7, "StrDeg": 0.6, "inf_DP": 5.749023, "Distance_ref": 45.24, "TgtSpeed_ref": 86.94, "TgtXPos_LeftUp": 441.0, "TgtYPos_LeftUp": 23.0, "TgtWidth": 89.0, "TgtHeight": 134.0}, {"OwnSpeed": 90.6, "StrDeg": 0.5, "inf_DP": 5.749023, "Distance_ref": 45.12, "TgtSpeed_ref": 86.92, "TgtXPos_LeftUp": 441.0, "TgtYPos_LeftUp": 23.0, "TgtWidth": 90.0, "TgtHeight": 134.0}, {"OwnSpeed": 90.4, "StrDeg": 0.6, "inf_DP": 5.749023, "Distance_ref": 45.02, "TgtSpeed_ref": 86.87, "TgtXPos_LeftUp": 440.0, "TgtYPos_LeftUp": 21.0, "TgtWidth": 90.0, "TgtHeight": 135.0}, {"OwnSpeed": 90.3, "StrDeg": 0.5, "inf_DP": 5.749023, "Distance_ref": 44.92, "TgtSpeed_ref": 86.83, "TgtXPos_LeftUp": 440.0, "TgtYPos_LeftUp": 20.0, "TgtWidth": 90.0, "TgtHeight": 136.0}, {"OwnSpeed": 90.2, "StrDeg": 0.6, "inf_DP": 5.749023, "Distance_ref": 44.82, "TgtSpeed_ref": 86.82, "TgtXPos_LeftUp": 440.0, "TgtYPos_LeftUp": 21.0, "TgtWidth": 90.0, "TgtHeight": 135.0}, {"OwnSpeed": 90.1, "StrDeg": 0.5, "inf_DP": 5.749023, "Distance_ref": 44.72, "TgtSpeed_ref": 86.81, "TgtXPos_LeftUp": 439.0, "TgtYPos_LeftUp": 22.0, "TgtWidth": 91.0, "TgtHeight": 135.0}, {"OwnSpeed": 90.0, "StrDeg": 0.5, "inf_DP": 5.749023, "Distance_ref": 44.62, "TgtSpeed_ref": 86.8, "TgtXPos_LeftUp": 438.0, "TgtYPos_LeftUp": 21.0, "TgtWidth": 91.0, "TgtHeight": 136.0}, {"OwnSpeed": 89.9, "StrDeg": 0.6, "inf_DP": 5.749023, "Distance_ref": 44.55, "TgtSpeed_ref": 86.76, "TgtXPos_LeftUp": 438.0, "TgtYPos_LeftUp": 20.0, "TgtWidth": 91.0, "TgtHeight": 136.0}, {"OwnSpeed": 89.8, "StrDeg": 0.6, "inf_DP": 5.749023, "Distance_ref": 44.48, "TgtSpeed_ref": 86.76, "TgtXPos_LeftUp": 437.0, "TgtYPos_LeftUp": 21.0, "TgtWidth": 91.0, "TgtHeight": 136.0}, {"OwnSpeed": 89.7, "StrDeg": 0.6, "inf_DP": 5.749023, "Distance_ref": 44.39, "TgtSpeed_ref": 86.76, "TgtXPos_LeftUp": 436.0, "TgtYPos_LeftUp": 22.0, "TgtWidth": 92.0, "TgtHeight": 137.0}, {"OwnSpeed": 89.6, "StrDeg": 0.6, "inf_DP": 5.749023, "Distance_ref": 44.31, "TgtSpeed_ref": 86.77, "TgtXPos_LeftUp": 436.0, "TgtYPos_LeftUp": 22.0, "TgtWidth": 92.0, "TgtHeight": 137.0}, {"OwnSpeed": 89.5, "StrDeg": 0.6, "inf_DP": 5.749023, "Distance_ref": 44.24, "TgtSpeed_ref": 86.75, "TgtXPos_LeftUp": 435.0, "TgtYPos_LeftUp": 22.0, "TgtWidth": 93.0, "TgtHeight": 138.0}, {"OwnSpeed": 89.4, "StrDeg": 0.1, "inf_DP": 5.749023, "Distance_ref": 44.16, "TgtSpeed_ref": 86.77, "TgtXPos_LeftUp": 435.0, "TgtYPos_LeftUp": 23.0, "TgtWidth": 93.0, "TgtHeight": 137.0}, {"OwnSpeed": 89.3, "StrDeg": -0.2, "inf_DP": 5.749023, "Distance_ref": 44.11, "TgtSpeed_ref": 86.75, "TgtXPos_LeftUp": 436.0, "TgtYPos_LeftUp": 22.0, "TgtWidth": 93.0, "TgtHeight": 138.0}, {"OwnSpeed": 89.2, "StrDeg": -0.2, "inf_DP": 5.749023, "Distance_ref": 44.04, "TgtSpeed_ref": 86.76, "TgtXPos_LeftUp": 437.0, "TgtYPos_LeftUp": 22.0, "TgtWidth": 93.0, "TgtHeight": 138.0}, {"OwnSpeed": 89.2, "StrDeg": -0.2, "inf_DP": 5.749023, "Distance_ref": 43.96, "TgtSpeed_ref": 86.75, "TgtXPos_LeftUp": 439.0, "TgtYPos_LeftUp": 24.0, "TgtWidth": 93.0, "TgtHeight": 137.0}, {"OwnSpeed": 89.1, "StrDeg": -0.2, "inf_DP": 5.749023, "Distance_ref": 43.89, "TgtSpeed_ref": 86.75, "TgtXPos_LeftUp": 441.0, "TgtYPos_LeftUp": 27.0, "TgtWidth": 92.0, "TgtHeight": 137.0}, {"OwnSpeed": 89.0, "StrDeg": -0.1, "inf_DP": 5.749023, "Distance_ref": 43.84, "TgtSpeed_ref": 86.76, "TgtXPos_LeftUp": 442.0, "TgtYPos_LeftUp": 26.0, "TgtWidth": 92.0, "TgtHeight": 137.0}, {"OwnSpeed": 88.9, "StrDeg": -0.1, "inf_DP": 5.749023, "Distance_ref": 43.76, "TgtSpeed_ref": 86.82, "TgtXPos_LeftUp": 444.0, "TgtYPos_LeftUp": 27.0, "TgtWidth": 92.0, "TgtHeight": 138.0}, {"OwnSpeed": 88.9, "StrDeg": -0.1, "inf_DP": 5.749023, "Distance_ref": 43.71, "TgtSpeed_ref": 86.83, "TgtXPos_LeftUp": 445.0, "TgtYPos_LeftUp": 27.0, "TgtWidth": 93.0, "TgtHeight": 137.0}, {"OwnSpeed": 88.8, "StrDeg": 0.0, "inf_DP": 5.749023, "Distance_ref": 43.64, "TgtSpeed_ref": 86.88, "TgtXPos_LeftUp": 446.0, "TgtYPos_LeftUp": 23.0, "TgtWidth": 94.0, "TgtHeight": 139.0}, {"OwnSpeed": 88.7, "StrDeg": 0.3, "inf_DP": 5.749023, "Distance_ref": 43.58, "TgtSpeed_ref": 86.89, "TgtXPos_LeftUp": 447.0, "TgtYPos_LeftUp": 20.0, "TgtWidth": 93.0, "TgtHeight": 139.0}, {"OwnSpeed": 88.7, "StrDeg": 1.0, "inf_DP": 5.749023, "Distance_ref": 43.54, "TgtSpeed_ref": 86.93, "TgtXPos_LeftUp": 448.0, "TgtYPos_LeftUp": 22.0, "TgtWidth": 93.0, "TgtHeight": 139.0}, {"OwnSpeed": 88.7, "StrDeg": 1.2, "inf_DP": 5.749023, "Distance_ref": 43.49, "TgtSpeed_ref": 87.05, "TgtXPos_LeftUp": 448.0, "TgtYPos_LeftUp": 22.0, "TgtWidth": 93.0, "TgtHeight": 139.0}, {"OwnSpeed": 88.5, "StrDeg": 1.2, "inf_DP": 5.749512, "Distance_ref": 43.45, "TgtSpeed_ref": 87.13, "TgtXPos_LeftUp": 447.0, "TgtYPos_LeftUp": 20.0, "TgtWidth": 94.0, "TgtHeight": 139.0}, {"OwnSpeed": 88.5, "StrDeg": 1.2, "inf_DP": 5.749512, "Distance_ref": 43.41, "TgtSpeed_ref": 87.14, "TgtXPos_LeftUp": 446.0, "TgtYPos_LeftUp": 19.0, "TgtWidth": 94.0, "TgtHeight": 140.0}, {"OwnSpeed": 88.4, "StrDeg": 1.2, "inf_DP": 5.749512, "Distance_ref": 43.38, "TgtSpeed_ref": 87.17, "TgtXPos_LeftUp": 445.0, "TgtYPos_LeftUp": 19.0, "TgtWidth": 94.0, "TgtHeight": 140.0}, {"OwnSpeed": 88.4, "StrDeg": 1.2, "inf_DP": 5.749512, "Distance_ref": 43.35, "TgtSpeed_ref": 87.14, "TgtXPos_LeftUp": 444.0, "TgtYPos_LeftUp": 21.0, "TgtWidth": 94.0, "TgtHeight": 140.0}, {"OwnSpeed": 88.4, "StrDeg": 1.2, "inf_DP": 5.749512, "Distance_ref": 43.33, "TgtSpeed_ref": 87.15, "TgtXPos_LeftUp": 444.0, "TgtYPos_LeftUp": 21.0, "TgtWidth": 94.0, "TgtHeight": 140.0}, {"OwnSpeed": 88.3, "StrDeg": 1.2, "inf_DP": 5.749512, "Distance_ref": 43.3, "TgtSpeed_ref": 87.13, "TgtXPos_LeftUp": 443.0, "TgtYPos_LeftUp": 17.0, "TgtWidth": 94.0, "TgtHeight": 140.0}, {"OwnSpeed": 88.3, "StrDeg": 1.2, "inf_DP": 5.749512, "Distance_ref": 43.3, "TgtSpeed_ref": 87.01, "TgtXPos_LeftUp": 442.0, "TgtYPos_LeftUp": 20.0, "TgtWidth": 94.0, "TgtHeight": 140.0}, {"OwnSpeed": 88.2, "StrDeg": 1.2, "inf_DP": 5.749512, "Distance_ref": 43.29, "TgtSpeed_ref": 86.91, "TgtXPos_LeftUp": 442.0, "TgtYPos_LeftUp": 18.0, "TgtWidth": 94.0, "TgtHeight": 141.0}, {"OwnSpeed": 88.0, "StrDeg": 1.2, "inf_DP": 5.749756, "Distance_ref": 43.26, "TgtSpeed_ref": 86.87, "TgtXPos_LeftUp": 441.0, "TgtYPos_LeftUp": 10.0, "TgtWidth": 94.0, "TgtHeight": 140.0}, {"OwnSpeed": 88.0, "StrDeg": 1.2, "inf_DP": 5.749756, "Distance_ref": 43.23, "TgtSpeed_ref": 86.8, "TgtXPos_LeftUp": 440.0, "TgtYPos_LeftUp": 11.0, "TgtWidth": 95.0, "TgtHeight": 141.0}, {"OwnSpeed": 88.1, "StrDeg": 1.2, "inf_DP": 5.749756, "Distance_ref": 43.18, "TgtSpeed_ref": 86.77, "TgtXPos_LeftUp": 440.0, "TgtYPos_LeftUp": 18.0, "TgtWidth": 94.0, "TgtHeight": 141.0}, {"OwnSpeed": 88.0, "StrDeg": 1.2, "inf_DP": 5.749756, "Distance_ref": 43.14, "TgtSpeed_ref": 86.71, "TgtXPos_LeftUp": 439.0, "TgtYPos_LeftUp": 22.0, "TgtWidth": 95.0, "TgtHeight": 141.0}, {"OwnSpeed": 87.9, "StrDeg": 1.2, "inf_DP": 5.749756, "Distance_ref": 43.09, "TgtSpeed_ref": 86.65, "TgtXPos_LeftUp": 439.0, "TgtYPos_LeftUp": 22.0, "TgtWidth": 95.0, "TgtHeight": 141.0}, {"OwnSpeed": 87.9, "StrDeg": 1.2, "inf_DP": 5.749756, "Distance_ref": 43.02, "TgtSpeed_ref": 86.64, "TgtXPos_LeftUp": 439.0, "TgtYPos_LeftUp": 22.0, "TgtWidth": 95.0, "TgtHeight": 141.0}, {"OwnSpeed": 87.8, "StrDeg": 1.0, "inf_DP": 5.749756, "Distance_ref": 42.96, "TgtSpeed_ref": 86.55, "TgtXPos_LeftUp": 439.0, "TgtYPos_LeftUp": 23.0, "TgtWidth": 95.0, "TgtHeight": 141.0}, {"OwnSpeed": 87.8, "StrDeg": 0.6, "inf_DP": 5.749756, "Distance_ref": 42.92, "TgtSpeed_ref": 86.5, "TgtXPos_LeftUp": 439.0, "TgtYPos_LeftUp": 21.0, "TgtWidth": 95.0, "TgtHeight": 141.0}, {"OwnSpeed": 87.8, "StrDeg": 0.2, "inf_DP": 5.75, "Distance_ref": 42.88, "TgtSpeed_ref": 86.52, "TgtXPos_LeftUp": 440.0, "TgtYPos_LeftUp": 21.0, "TgtWidth": 96.0, "TgtHeight": 141.0}, {"OwnSpeed": 87.7, "StrDeg": 0.2, "inf_DP": 5.75, "Distance_ref": 42.85, "TgtSpeed_ref": 86.57, "TgtXPos_LeftUp": 442.0, "TgtYPos_LeftUp": 21.0, "TgtWidth": 95.0, "TgtHeight": 141.0}, {"OwnSpeed": 87.6, "StrDeg": 0.2, "inf_DP": 5.75, "Distance_ref": 42.82, "TgtSpeed_ref": 86.6, "TgtXPos_LeftUp": 444.0, "TgtYPos_LeftUp": 21.0, "TgtWidth": 95.0, "TgtHeight": 141.0}, {"OwnSpeed": 87.6, "StrDeg": 0.2, "inf_DP": 5.75, "Distance_ref": 42.79, "TgtSpeed_ref": 86.64, "TgtXPos_LeftUp": 445.0, "TgtYPos_LeftUp": 21.0, "TgtWidth": 95.0, "TgtHeight": 142.0}, {"OwnSpeed": 87.6, "StrDeg": 0.2, "inf_DP": 5.75, "Distance_ref": 42.78, "TgtSpeed_ref": 86.67, "TgtXPos_LeftUp": 447.0, "TgtYPos_LeftUp": 22.0, "TgtWidth": 95.0, "TgtHeight": 141.0}, {"OwnSpeed": 87.5, "StrDeg": 0.2, "inf_DP": 5.75, "Distance_ref": 42.76, "TgtSpeed_ref": 86.78, "TgtXPos_LeftUp": 448.0, "TgtYPos_LeftUp": 22.0, "TgtWidth": 95.0, "TgtHeight": 141.0}, {"OwnSpeed": 87.5, "StrDeg": 0.2, "inf_DP": 5.75, "Distance_ref": 42.75, "TgtSpeed_ref": 86.85, "TgtXPos_LeftUp": 449.0, "TgtYPos_LeftUp": 22.0, "TgtWidth": 95.0, "TgtHeight": 141.0}, {"OwnSpeed": 87.5, "StrDeg": 0.2, "inf_DP": 5.75, "Distance_ref": 42.75, "TgtSpeed_ref": 86.86, "TgtXPos_LeftUp": 450.0, "TgtYPos_LeftUp": 22.0, "TgtWidth": 95.0, "TgtHeight": 141.0}, {"OwnSpeed": 87.5, "StrDeg": 0.3, "inf_DP": 5.75, "Distance_ref": 42.75, "TgtSpeed_ref": 86.87, "TgtXPos_LeftUp": 450.0, "TgtYPos_LeftUp": 22.0, "TgtWidth": 95.0, "TgtHeight": 141.0}, {"OwnSpeed": 87.4, "StrDeg": 0.4, "inf_DP": 5.750244, "Distance_ref": 42.74, "TgtSpeed_ref": 86.88, "TgtXPos_LeftUp": 450.0, "TgtYPos_LeftUp": 20.0, "TgtWidth": 95.0, "TgtHeight": 142.0}, {"OwnSpeed": 87.4, "StrDeg": 0.5, "inf_DP": 5.750488, "Distance_ref": 42.72, "TgtSpeed_ref": 86.9, "TgtXPos_LeftUp": 450.0, "TgtYPos_LeftUp": 20.0, "TgtWidth": 95.0, "TgtHeight": 142.0}, {"OwnSpeed": 87.4, "StrDeg": 0.6, "inf_DP": 5.750488, "Distance_ref": 42.71, "TgtSpeed_ref": 86.92, "TgtXPos_LeftUp": 450.0, "TgtYPos_LeftUp": 20.0, "TgtWidth": 95.0, "TgtHeight": 142.0}, {"OwnSpeed": 87.4, "StrDeg": 0.6, "inf_DP": 5.750488, "Distance_ref": 42.69, "TgtSpeed_ref": 86.9, "TgtXPos_LeftUp": 450.0, "TgtYPos_LeftUp": 20.0, "TgtWidth": 95.0, "TgtHeight": 142.0}, {"OwnSpeed": 87.4, "StrDeg": 0.6, "inf_DP": 5.750488, "Distance_ref": 42.68, "TgtSpeed_ref": 86.89, "TgtXPos_LeftUp": 450.0, "TgtYPos_LeftUp": 21.0, "TgtWidth": 95.0, "TgtHeight": 141.0}, {"OwnSpeed": 87.4, "StrDeg": 0.6, "inf_DP": 5.750488, "Distance_ref": 42.65, "TgtSpeed_ref": 86.91, "TgtXPos_LeftUp": 450.0, "TgtYPos_LeftUp": 20.0, "TgtWidth": 95.0, "TgtHeight": 142.0}, {"OwnSpeed": 87.4, "StrDeg": 0.6, "inf_DP": 5.750488, "Distance_ref": 42.62, "TgtSpeed_ref": 86.89, "TgtXPos_LeftUp": 450.0, "TgtYPos_LeftUp": 20.0, "TgtWidth": 95.0, "TgtHeight": 142.0}, {"OwnSpeed": 87.4, "StrDeg": 0.6, "inf_DP": 5.750732, "Distance_ref": 42.61, "TgtSpeed_ref": 86.87, "TgtXPos_LeftUp": 450.0, "TgtYPos_LeftUp": 21.0, "TgtWidth": 95.0, "TgtHeight": 142.0}, {"OwnSpeed": 87.4, "StrDeg": 0.6, "inf_DP": 5.750977, "Distance_ref": 42.59, "TgtSpeed_ref": 86.88, "TgtXPos_LeftUp": 450.0, "TgtYPos_LeftUp": 20.0, "TgtWidth": 95.0, "TgtHeight": 142.0}, {"OwnSpeed": 87.3, "StrDeg": 0.6, "inf_DP": 5.750977, "Distance_ref": 42.58, "TgtSpeed_ref": 86.86, "TgtXPos_LeftUp": 450.0, "TgtYPos_LeftUp": 20.0, "TgtWidth": 95.0, "TgtHeight": 142.0}, {"OwnSpeed": 87.3, "StrDeg": 0.7, "inf_DP": 5.751221, "Distance_ref": 42.56, "TgtSpeed_ref": 86.83, "TgtXPos_LeftUp": 450.0, "TgtYPos_LeftUp": 21.0, "TgtWidth": 95.0, "TgtHeight": 143.0}, {"OwnSpeed": 87.3, "StrDeg": 0.6, "inf_DP": 5.751221, "Distance_ref": 42.55, "TgtSpeed_ref": 86.81, "TgtXPos_LeftUp": 450.0, "TgtYPos_LeftUp": 21.0, "TgtWidth": 95.0, "TgtHeight": 142.0}, {"OwnSpeed": 87.3, "StrDeg": 0.6, "inf_DP": 5.751221, "Distance_ref": 42.55, "TgtSpeed_ref": 86.77, "TgtXPos_LeftUp": 450.0, "TgtYPos_LeftUp": 20.0, "TgtWidth": 95.0, "TgtHeight": 142.0}, {"OwnSpeed": 87.2, "StrDeg": 0.6, "inf_DP": 5.751221, "Distance_ref": 42.55, "TgtSpeed_ref": 86.71, "TgtXPos_LeftUp": 450.0, "TgtYPos_LeftUp": 20.0, "TgtWidth": 94.0, "TgtHeight": 142.0}, {"OwnSpeed": 87.2, "StrDeg": 0.6, "inf_DP": 5.751221, "Distance_ref": 42.55, "TgtSpeed_ref": 86.74, "TgtXPos_LeftUp": 449.0, "TgtYPos_LeftUp": 20.0, "TgtWidth": 95.0, "TgtHeight": 142.0}, {"OwnSpeed": 87.1, "StrDeg": 0.6, "inf_DP": 5.751221, "Distance_ref": 42.55, "TgtSpeed_ref": 86.74, "TgtXPos_LeftUp": 448.0, "TgtYPos_LeftUp": 20.0, "TgtWidth": 96.0, "TgtHeight": 142.0}, {"OwnSpeed": 87.1, "StrDeg": 0.6, "inf_DP": 5.751221, "Distance_ref": 42.54, "TgtSpeed_ref": 86.73, "TgtXPos_LeftUp": 448.0, "TgtYPos_LeftUp": 20.0, "TgtWidth": 95.0, "TgtHeight": 142.0}]}