{"attributes": {"評価値計算時の重み付加": "無"}, "sequence": [{"OwnSpeed": 93.4, "StrDeg": -2.7, "inf_DP": 5.768555, "Distance_ref": 83.81, "TgtSpeed_ref": 76.26, "TgtXPos_LeftUp": 436.0, "TgtYPos_LeftUp": 56.0, "TgtWidth": 52.0, "TgtHeight": 75.0}, {"OwnSpeed": 93.3, "StrDeg": -2.7, "inf_DP": 5.768555, "Distance_ref": 83.31, "TgtSpeed_ref": 76.38, "TgtXPos_LeftUp": 436.0, "TgtYPos_LeftUp": 54.0, "TgtWidth": 52.0, "TgtHeight": 76.0}, {"OwnSpeed": 93.2, "StrDeg": -2.7, "inf_DP": 5.768555, "Distance_ref": 82.81, "TgtSpeed_ref": 76.34, "TgtXPos_LeftUp": 436.0, "TgtYPos_LeftUp": 54.0, "TgtWidth": 53.0, "TgtHeight": 76.0}, {"OwnSpeed": 93.1, "StrDeg": -2.7, "inf_DP": 5.768555, "Distance_ref": 82.36, "TgtSpeed_ref": 76.17, "TgtXPos_LeftUp": 437.0, "TgtYPos_LeftUp": 55.0, "TgtWidth": 52.0, "TgtHeight": 76.0}, {"OwnSpeed": 93.0, "StrDeg": -2.7, "inf_DP": 5.768555, "Distance_ref": 81.92, "TgtSpeed_ref": 76.17, "TgtXPos_LeftUp": 438.0, "TgtYPos_LeftUp": 54.0, "TgtWidth": 52.0, "TgtHeight": 76.0}, {"OwnSpeed": 92.9, "StrDeg": -2.7, "inf_DP": 5.768555, "Distance_ref": 81.46, "TgtSpeed_ref": 76.18, "TgtXPos_LeftUp": 438.0, "TgtYPos_LeftUp": 53.0, "TgtWidth": 52.0, "TgtHeight": 77.0}, {"OwnSpeed": 92.9, "StrDeg": -2.7, "inf_DP": 5.768555, "Distance_ref": 80.96, "TgtSpeed_ref": 76.15, "TgtXPos_LeftUp": 438.0, "TgtYPos_LeftUp": 52.0, "TgtWidth": 53.0, "TgtHeight": 78.0}, {"OwnSpeed": 92.8, "StrDeg": -2.6, "inf_DP": 5.768555, "Distance_ref": 80.46, "TgtSpeed_ref": 76.12, "TgtXPos_LeftUp": 438.0, "TgtYPos_LeftUp": 54.0, "TgtWidth": 54.0, "TgtHeight": 78.0}, {"OwnSpeed": 92.6, "StrDeg": -2.6, "inf_DP": 5.768555, "Distance_ref": 80.02, "TgtSpeed_ref": 75.98, "TgtXPos_LeftUp": 438.0, "TgtYPos_LeftUp": 52.0, "TgtWidth": 54.0, "TgtHeight": 79.0}, {"OwnSpeed": 92.5, "StrDeg": -2.6, "inf_DP": 5.768555, "Distance_ref": 79.59, "TgtSpeed_ref": 75.98, "TgtXPos_LeftUp": 438.0, "TgtYPos_LeftUp": 50.0, "TgtWidth": 54.0, "TgtHeight": 79.0}, {"OwnSpeed": 92.4, "StrDeg": -2.6, "inf_DP": 5.768555, "Distance_ref": 79.11, "TgtSpeed_ref": 76.11, "TgtXPos_LeftUp": 438.0, "TgtYPos_LeftUp": 51.0, "TgtWidth": 55.0, "TgtHeight": 79.0}, {"OwnSpeed": 92.3, "StrDeg": -2.6, "inf_DP": 5.768555, "Distance_ref": 78.64, "TgtSpeed_ref": 76.11, "TgtXPos_LeftUp": 438.0, "TgtYPos_LeftUp": 50.0, "TgtWidth": 55.0, "TgtHeight": 79.0}, {"OwnSpeed": 92.2, "StrDeg": -2.6, "inf_DP": 5.768555, "Distance_ref": 78.16, "TgtSpeed_ref": 76.11, "TgtXPos_LeftUp": 438.0, "TgtYPos_LeftUp": 49.0, "TgtWidth": 56.0, "TgtHeight": 80.0}, {"OwnSpeed": 92.1, "StrDeg": -2.6, "inf_DP": 5.768555, "Distance_ref": 77.75, "TgtSpeed_ref": 76.0, "TgtXPos_LeftUp": 438.0, "TgtYPos_LeftUp": 50.0, "TgtWidth": 56.0, "TgtHeight": 80.0}, {"OwnSpeed": 92.0, "StrDeg": -2.6, "inf_DP": 5.768555, "Distance_ref": 77.34, "TgtSpeed_ref": 76.02, "TgtXPos_LeftUp": 439.0, "TgtYPos_LeftUp": 50.0, "TgtWidth": 56.0, "TgtHeight": 81.0}, {"OwnSpeed": 91.9, "StrDeg": -2.6, "inf_DP": 5.768555, "Distance_ref": 76.88, "TgtSpeed_ref": 76.15, "TgtXPos_LeftUp": 439.0, "TgtYPos_LeftUp": 49.0, "TgtWidth": 57.0, "TgtHeight": 82.0}, {"OwnSpeed": 91.7, "StrDeg": -2.6, "inf_DP": 5.768555, "Distance_ref": 76.42, "TgtSpeed_ref": 76.15, "TgtXPos_LeftUp": 439.0, "TgtYPos_LeftUp": 51.0, "TgtWidth": 57.0, "TgtHeight": 82.0}, {"OwnSpeed": 91.6, "StrDeg": -2.6, "inf_DP": 5.768555, "Distance_ref": 76.02, "TgtSpeed_ref": 76.03, "TgtXPos_LeftUp": 440.0, "TgtYPos_LeftUp": 51.0, "TgtWidth": 57.0, "TgtHeight": 83.0}, {"OwnSpeed": 91.5, "StrDeg": -2.6, "inf_DP": 5.768555, "Distance_ref": 75.62, "TgtSpeed_ref": 76.06, "TgtXPos_LeftUp": 440.0, "TgtYPos_LeftUp": 50.0, "TgtWidth": 57.0, "TgtHeight": 83.0}, {"OwnSpeed": 91.4, "StrDeg": -2.6, "inf_DP": 5.768555, "Distance_ref": 75.22, "TgtSpeed_ref": 76.05, "TgtXPos_LeftUp": 440.0, "TgtYPos_LeftUp": 50.0, "TgtWidth": 58.0, "TgtHeight": 84.0}, {"OwnSpeed": 91.3, "StrDeg": -2.6, "inf_DP": 5.768555, "Distance_ref": 74.76, "TgtSpeed_ref": 76.18, "TgtXPos_LeftUp": 440.0, "TgtYPos_LeftUp": 50.0, "TgtWidth": 59.0, "TgtHeight": 84.0}, {"OwnSpeed": 91.2, "StrDeg": -2.6, "inf_DP": 5.768555, "Distance_ref": 74.32, "TgtSpeed_ref": 76.17, "TgtXPos_LeftUp": 441.0, "TgtYPos_LeftUp": 50.0, "TgtWidth": 58.0, "TgtHeight": 85.0}, {"OwnSpeed": 91.1, "StrDeg": -2.6, "inf_DP": 5.768555, "Distance_ref": 73.92, "TgtSpeed_ref": 76.06, "TgtXPos_LeftUp": 441.0, "TgtYPos_LeftUp": 49.0, "TgtWidth": 59.0, "TgtHeight": 85.0}, {"OwnSpeed": 91.0, "StrDeg": -2.5, "inf_DP": 5.768555, "Distance_ref": 73.52, "TgtSpeed_ref": 76.04, "TgtXPos_LeftUp": 441.0, "TgtYPos_LeftUp": 49.0, "TgtWidth": 59.0, "TgtHeight": 86.0}, {"OwnSpeed": 90.8, "StrDeg": -2.4, "inf_DP": 5.768555, "Distance_ref": 73.09, "TgtSpeed_ref": 76.13, "TgtXPos_LeftUp": 441.0, "TgtYPos_LeftUp": 49.0, "TgtWidth": 59.0, "TgtHeight": 86.0}, {"OwnSpeed": 90.7, "StrDeg": -2.4, "inf_DP": 5.768555, "Distance_ref": 72.66, "TgtSpeed_ref": 76.08, "TgtXPos_LeftUp": 441.0, "TgtYPos_LeftUp": 49.0, "TgtWidth": 59.0, "TgtHeight": 86.0}, {"OwnSpeed": 90.6, "StrDeg": -2.4, "inf_DP": 5.768555, "Distance_ref": 72.24, "TgtSpeed_ref": 76.06, "TgtXPos_LeftUp": 441.0, "TgtYPos_LeftUp": 50.0, "TgtWidth": 60.0, "TgtHeight": 87.0}, {"OwnSpeed": 90.6, "StrDeg": -2.4, "inf_DP": 5.768555, "Distance_ref": 71.86, "TgtSpeed_ref": 75.94, "TgtXPos_LeftUp": 441.0, "TgtYPos_LeftUp": 52.0, "TgtWidth": 60.0, "TgtHeight": 87.0}, {"OwnSpeed": 90.4, "StrDeg": -2.4, "inf_DP": 5.768555, "Distance_ref": 71.49, "TgtSpeed_ref": 75.95, "TgtXPos_LeftUp": 441.0, "TgtYPos_LeftUp": 54.0, "TgtWidth": 60.0, "TgtHeight": 87.0}, {"OwnSpeed": 90.3, "StrDeg": -2.4, "inf_DP": 5.768555, "Distance_ref": 71.08, "TgtSpeed_ref": 76.1, "TgtXPos_LeftUp": 441.0, "TgtYPos_LeftUp": 54.0, "TgtWidth": 60.0, "TgtHeight": 88.0}, {"OwnSpeed": 90.1, "StrDeg": -2.4, "inf_DP": 5.768555, "Distance_ref": 70.66, "TgtSpeed_ref": 76.15, "TgtXPos_LeftUp": 441.0, "TgtYPos_LeftUp": 53.0, "TgtWidth": 61.0, "TgtHeight": 89.0}, {"OwnSpeed": 90.0, "StrDeg": -2.4, "inf_DP": 5.768555, "Distance_ref": 70.29, "TgtSpeed_ref": 76.09, "TgtXPos_LeftUp": 441.0, "TgtYPos_LeftUp": 54.0, "TgtWidth": 61.0, "TgtHeight": 89.0}, {"OwnSpeed": 89.8, "StrDeg": -2.3, "inf_DP": 5.768555, "Distance_ref": 69.92, "TgtSpeed_ref": 76.14, "TgtXPos_LeftUp": 441.0, "TgtYPos_LeftUp": 54.0, "TgtWidth": 62.0, "TgtHeight": 89.0}, {"OwnSpeed": 89.7, "StrDeg": -2.3, "inf_DP": 5.768555, "Distance_ref": 69.56, "TgtSpeed_ref": 76.18, "TgtXPos_LeftUp": 441.0, "TgtYPos_LeftUp": 54.0, "TgtWidth": 62.0, "TgtHeight": 89.0}, {"OwnSpeed": 89.6, "StrDeg": -2.2, "inf_DP": 5.768555, "Distance_ref": 69.16, "TgtSpeed_ref": 76.31, "TgtXPos_LeftUp": 442.0, "TgtYPos_LeftUp": 54.0, "TgtWidth": 62.0, "TgtHeight": 90.0}, {"OwnSpeed": 89.4, "StrDeg": -2.2, "inf_DP": 5.768555, "Distance_ref": 68.76, "TgtSpeed_ref": 76.33, "TgtXPos_LeftUp": 442.0, "TgtYPos_LeftUp": 52.0, "TgtWidth": 62.0, "TgtHeight": 91.0}, {"OwnSpeed": 89.3, "StrDeg": -2.2, "inf_DP": 5.768555, "Distance_ref": 68.44, "TgtSpeed_ref": 76.22, "TgtXPos_LeftUp": 442.0, "TgtYPos_LeftUp": 54.0, "TgtWidth": 62.0, "TgtHeight": 91.0}, {"OwnSpeed": 89.2, "StrDeg": -2.2, "inf_DP": 5.768555, "Distance_ref": 68.11, "TgtSpeed_ref": 76.21, "TgtXPos_LeftUp": 442.0, "TgtYPos_LeftUp": 57.0, "TgtWidth": 63.0, "TgtHeight": 92.0}, {"OwnSpeed": 89.1, "StrDeg": -2.2, "inf_DP": 5.768555, "Distance_ref": 67.74, "TgtSpeed_ref": 76.33, "TgtXPos_LeftUp": 442.0, "TgtYPos_LeftUp": 61.0, "TgtWidth": 63.0, "TgtHeight": 93.0}, {"OwnSpeed": 89.0, "StrDeg": -2.2, "inf_DP": 5.768555, "Distance_ref": 67.38, "TgtSpeed_ref": 76.34, "TgtXPos_LeftUp": 442.0, "TgtYPos_LeftUp": 65.0, "TgtWidth": 64.0, "TgtHeight": 92.0}, {"OwnSpeed": 88.8, "StrDeg": -2.1, "inf_DP": 5.768555, "Distance_ref": 67.02, "TgtSpeed_ref": 76.35, "TgtXPos_LeftUp": 442.0, "TgtYPos_LeftUp": 60.0, "TgtWidth": 64.0, "TgtHeight": 93.0}, {"OwnSpeed": 88.4, "StrDeg": -2.1, "inf_DP": 5.768555, "Distance_ref": 66.71, "TgtSpeed_ref": 76.26, "TgtXPos_LeftUp": 442.0, "TgtYPos_LeftUp": 48.0, "TgtWidth": 65.0, "TgtHeight": 92.0}, {"OwnSpeed": 88.3, "StrDeg": -2.1, "inf_DP": 5.768555, "Distance_ref": 66.41, "TgtSpeed_ref": 76.23, "TgtXPos_LeftUp": 442.0, "TgtYPos_LeftUp": 42.0, "TgtWidth": 65.0, "TgtHeight": 93.0}, {"OwnSpeed": 88.2, "StrDeg": -2.1, "inf_DP": 5.768555, "Distance_ref": 66.05, "TgtSpeed_ref": 76.35, "TgtXPos_LeftUp": 441.0, "TgtYPos_LeftUp": 40.0, "TgtWidth": 66.0, "TgtHeight": 94.0}, {"OwnSpeed": 88.2, "StrDeg": -2.0, "inf_DP": 5.768555, "Distance_ref": 65.69, "TgtSpeed_ref": 76.3, "TgtXPos_LeftUp": 441.0, "TgtYPos_LeftUp": 42.0, "TgtWidth": 66.0, "TgtHeight": 94.0}, {"OwnSpeed": 88.2, "StrDeg": -1.9, "inf_DP": 5.768555, "Distance_ref": 65.38, "TgtSpeed_ref": 76.29, "TgtXPos_LeftUp": 441.0, "TgtYPos_LeftUp": 49.0, "TgtWidth": 67.0, "TgtHeight": 95.0}, {"OwnSpeed": 88.1, "StrDeg": -1.9, "inf_DP": 5.768555, "Distance_ref": 65.06, "TgtSpeed_ref": 76.28, "TgtXPos_LeftUp": 441.0, "TgtYPos_LeftUp": 51.0, "TgtWidth": 67.0, "TgtHeight": 95.0}, {"OwnSpeed": 87.9, "StrDeg": -1.9, "inf_DP": 5.768555, "Distance_ref": 64.75, "TgtSpeed_ref": 76.24, "TgtXPos_LeftUp": 441.0, "TgtYPos_LeftUp": 47.0, "TgtWidth": 67.0, "TgtHeight": 95.0}, {"OwnSpeed": 87.8, "StrDeg": -1.9, "inf_DP": 5.768555, "Distance_ref": 64.41, "TgtSpeed_ref": 76.29, "TgtXPos_LeftUp": 441.0, "TgtYPos_LeftUp": 45.0, "TgtWidth": 67.0, "TgtHeight": 96.0}, {"OwnSpeed": 87.7, "StrDeg": -1.9, "inf_DP": 5.768555, "Distance_ref": 64.05, "TgtSpeed_ref": 76.27, "TgtXPos_LeftUp": 441.0, "TgtYPos_LeftUp": 47.0, "TgtWidth": 68.0, "TgtHeight": 96.0}, {"OwnSpeed": 87.6, "StrDeg": -1.9, "inf_DP": 5.768555, "Distance_ref": 63.75, "TgtSpeed_ref": 76.15, "TgtXPos_LeftUp": 441.0, "TgtYPos_LeftUp": 44.0, "TgtWidth": 68.0, "TgtHeight": 96.0}, {"OwnSpeed": 87.5, "StrDeg": -1.9, "inf_DP": 5.768555, "Distance_ref": 63.45, "TgtSpeed_ref": 76.2, "TgtXPos_LeftUp": 441.0, "TgtYPos_LeftUp": 44.0, "TgtWidth": 68.0, "TgtHeight": 97.0}, {"OwnSpeed": 87.5, "StrDeg": -1.9, "inf_DP": 5.768555, "Distance_ref": 63.16, "TgtSpeed_ref": 76.21, "TgtXPos_LeftUp": 441.0, "TgtYPos_LeftUp": 45.0, "TgtWidth": 69.0, "TgtHeight": 98.0}, {"OwnSpeed": 87.4, "StrDeg": -1.9, "inf_DP": 5.768555, "Distance_ref": 62.84, "TgtSpeed_ref": 76.2, "TgtXPos_LeftUp": 441.0, "TgtYPos_LeftUp": 46.0, "TgtWidth": 69.0, "TgtHeight": 98.0}, {"OwnSpeed": 87.3, "StrDeg": -1.9, "inf_DP": 5.768555, "Distance_ref": 62.51, "TgtSpeed_ref": 76.23, "TgtXPos_LeftUp": 442.0, "TgtYPos_LeftUp": 44.0, "TgtWidth": 69.0, "TgtHeight": 99.0}, {"OwnSpeed": 87.1, "StrDeg": -1.9, "inf_DP": 5.768555, "Distance_ref": 62.22, "TgtSpeed_ref": 76.17, "TgtXPos_LeftUp": 442.0, "TgtYPos_LeftUp": 40.0, "TgtWidth": 69.0, "TgtHeight": 99.0}, {"OwnSpeed": 87.0, "StrDeg": -1.8, "inf_DP": 5.768555, "Distance_ref": 61.94, "TgtSpeed_ref": 76.2, "TgtXPos_LeftUp": 442.0, "TgtYPos_LeftUp": 40.0, "TgtWidth": 70.0, "TgtHeight": 99.0}, {"OwnSpeed": 87.0, "StrDeg": -1.8, "inf_DP": 5.768555, "Distance_ref": 61.62, "TgtSpeed_ref": 76.33, "TgtXPos_LeftUp": 442.0, "TgtYPos_LeftUp": 43.0, "TgtWidth": 70.0, "TgtHeight": 100.0}, {"OwnSpeed": 86.9, "StrDeg": -1.7, "inf_DP": 5.769531, "Distance_ref": 61.32, "TgtSpeed_ref": 76.3, "TgtXPos_LeftUp": 442.0, "TgtYPos_LeftUp": 46.0, "TgtWidth": 71.0, "TgtHeight": 100.0}, {"OwnSpeed": 86.8, "StrDeg": -1.7, "inf_DP": 5.769531, "Distance_ref": 61.01, "TgtSpeed_ref": 76.3, "TgtXPos_LeftUp": 443.0, "TgtYPos_LeftUp": 45.0, "TgtWidth": 71.0, "TgtHeight": 101.0}, {"OwnSpeed": 86.6, "StrDeg": -1.7, "inf_DP": 5.769531, "Distance_ref": 60.74, "TgtSpeed_ref": 76.2, "TgtXPos_LeftUp": 443.0, "TgtYPos_LeftUp": 42.0, "TgtWidth": 71.0, "TgtHeight": 102.0}, {"OwnSpeed": 86.5, "StrDeg": -1.7, "inf_DP": 5.769531, "Distance_ref": 60.48, "TgtSpeed_ref": 76.19, "TgtXPos_LeftUp": 444.0, "TgtYPos_LeftUp": 41.0, "TgtWidth": 71.0, "TgtHeight": 102.0}, {"OwnSpeed": 86.4, "StrDeg": -1.6, "inf_DP": 5.769531, "Distance_ref": 60.18, "TgtSpeed_ref": 76.28, "TgtXPos_LeftUp": 444.0, "TgtYPos_LeftUp": 41.0, "TgtWidth": 72.0, "TgtHeight": 103.0}, {"OwnSpeed": 86.2, "StrDeg": -1.6, "inf_DP": 5.769531, "Distance_ref": 59.89, "TgtSpeed_ref": 76.28, "TgtXPos_LeftUp": 444.0, "TgtYPos_LeftUp": 38.0, "TgtWidth": 72.0, "TgtHeight": 102.0}, {"OwnSpeed": 86.1, "StrDeg": -1.6, "inf_DP": 5.769531, "Distance_ref": 59.64, "TgtSpeed_ref": 76.16, "TgtXPos_LeftUp": 444.0, "TgtYPos_LeftUp": 38.0, "TgtWidth": 72.0, "TgtHeight": 102.0}, {"OwnSpeed": 86.1, "StrDeg": -1.6, "inf_DP": 5.769531, "Distance_ref": 59.36, "TgtSpeed_ref": 76.14, "TgtXPos_LeftUp": 445.0, "TgtYPos_LeftUp": 40.0, "TgtWidth": 72.0, "TgtHeight": 105.0}, {"OwnSpeed": 86.0, "StrDeg": -1.5, "inf_DP": 5.769531, "Distance_ref": 59.11, "TgtSpeed_ref": 76.09, "TgtXPos_LeftUp": 445.0, "TgtYPos_LeftUp": 43.0, "TgtWidth": 73.0, "TgtHeight": 103.0}, {"OwnSpeed": 85.9, "StrDeg": -1.5, "inf_DP": 5.769531, "Distance_ref": 58.82, "TgtSpeed_ref": 76.15, "TgtXPos_LeftUp": 445.0, "TgtYPos_LeftUp": 41.0, "TgtWidth": 73.0, "TgtHeight": 106.0}, {"OwnSpeed": 85.7, "StrDeg": -1.4, "inf_DP": 5.769531, "Distance_ref": 58.54, "TgtSpeed_ref": 76.11, "TgtXPos_LeftUp": 446.0, "TgtYPos_LeftUp": 41.0, "TgtWidth": 72.0, "TgtHeight": 106.0}, {"OwnSpeed": 85.6, "StrDeg": -1.4, "inf_DP": 5.769531, "Distance_ref": 58.29, "TgtSpeed_ref": 75.95, "TgtXPos_LeftUp": 446.0, "TgtYPos_LeftUp": 42.0, "TgtWidth": 73.0, "TgtHeight": 106.0}, {"OwnSpeed": 85.5, "StrDeg": -1.4, "inf_DP": 5.769531, "Distance_ref": 58.05, "TgtSpeed_ref": 75.94, "TgtXPos_LeftUp": 446.0, "TgtYPos_LeftUp": 41.0, "TgtWidth": 73.0, "TgtHeight": 106.0}, {"OwnSpeed": 85.3, "StrDeg": -1.3, "inf_DP": 5.769531, "Distance_ref": 57.76, "TgtSpeed_ref": 76.01, "TgtXPos_LeftUp": 447.0, "TgtYPos_LeftUp": 39.0, "TgtWidth": 73.0, "TgtHeight": 104.0}, {"OwnSpeed": 85.2, "StrDeg": -1.2, "inf_DP": 5.769531, "Distance_ref": 57.49, "TgtSpeed_ref": 76.0, "TgtXPos_LeftUp": 447.0, "TgtYPos_LeftUp": 38.0, "TgtWidth": 73.0, "TgtHeight": 106.0}, {"OwnSpeed": 85.1, "StrDeg": -1.2, "inf_DP": 5.769531, "Distance_ref": 57.22, "TgtSpeed_ref": 76.03, "TgtXPos_LeftUp": 447.0, "TgtYPos_LeftUp": 40.0, "TgtWidth": 73.0, "TgtHeight": 108.0}, {"OwnSpeed": 85.1, "StrDeg": -1.0, "inf_DP": 5.769531, "Distance_ref": 56.98, "TgtSpeed_ref": 75.94, "TgtXPos_LeftUp": 447.0, "TgtYPos_LeftUp": 41.0, "TgtWidth": 74.0, "TgtHeight": 109.0}, {"OwnSpeed": 84.9, "StrDeg": -1.0, "inf_DP": 5.769531, "Distance_ref": 56.74, "TgtSpeed_ref": 75.92, "TgtXPos_LeftUp": 446.0, "TgtYPos_LeftUp": 38.0, "TgtWidth": 75.0, "TgtHeight": 106.0}, {"OwnSpeed": 84.7, "StrDeg": -1.0, "inf_DP": 5.769531, "Distance_ref": 56.46, "TgtSpeed_ref": 75.98, "TgtXPos_LeftUp": 446.0, "TgtYPos_LeftUp": 35.0, "TgtWidth": 75.0, "TgtHeight": 107.0}, {"OwnSpeed": 84.7, "StrDeg": -1.0, "inf_DP": 5.769531, "Distance_ref": 56.21, "TgtSpeed_ref": 75.93, "TgtXPos_LeftUp": 446.0, "TgtYPos_LeftUp": 37.0, "TgtWidth": 75.0, "TgtHeight": 107.0}, {"OwnSpeed": 84.6, "StrDeg": -0.9, "inf_DP": 5.769531, "Distance_ref": 55.99, "TgtSpeed_ref": 75.82, "TgtXPos_LeftUp": 446.0, "TgtYPos_LeftUp": 38.0, "TgtWidth": 76.0, "TgtHeight": 108.0}, {"OwnSpeed": 84.5, "StrDeg": -0.9, "inf_DP": 5.769531, "Distance_ref": 55.78, "TgtSpeed_ref": 75.85, "TgtXPos_LeftUp": 446.0, "TgtYPos_LeftUp": 41.0, "TgtWidth": 76.0, "TgtHeight": 107.0}, {"OwnSpeed": 84.4, "StrDeg": -0.9, "inf_DP": 5.769531, "Distance_ref": 55.56, "TgtSpeed_ref": 75.85, "TgtXPos_LeftUp": 446.0, "TgtYPos_LeftUp": 43.0, "TgtWidth": 76.0, "TgtHeight": 108.0}, {"OwnSpeed": 84.2, "StrDeg": -0.9, "inf_DP": 5.769531, "Distance_ref": 55.32, "TgtSpeed_ref": 75.92, "TgtXPos_LeftUp": 446.0, "TgtYPos_LeftUp": 40.0, "TgtWidth": 76.0, "TgtHeight": 109.0}, {"OwnSpeed": 84.1, "StrDeg": -0.9, "inf_DP": 5.769531, "Distance_ref": 55.08, "TgtSpeed_ref": 75.93, "TgtXPos_LeftUp": 446.0, "TgtYPos_LeftUp": 38.0, "TgtWidth": 77.0, "TgtHeight": 110.0}, {"OwnSpeed": 83.9, "StrDeg": -0.9, "inf_DP": 5.769531, "Distance_ref": 54.86, "TgtSpeed_ref": 75.89, "TgtXPos_LeftUp": 446.0, "TgtYPos_LeftUp": 34.0, "TgtWidth": 77.0, "TgtHeight": 110.0}, {"OwnSpeed": 83.9, "StrDeg": -0.9, "inf_DP": 5.769531, "Distance_ref": 54.65, "TgtSpeed_ref": 75.92, "TgtXPos_LeftUp": 446.0, "TgtYPos_LeftUp": 33.0, "TgtWidth": 77.0, "TgtHeight": 111.0}, {"OwnSpeed": 83.8, "StrDeg": -0.9, "inf_DP": 5.769531, "Distance_ref": 54.41, "TgtSpeed_ref": 75.98, "TgtXPos_LeftUp": 446.0, "TgtYPos_LeftUp": 36.0, "TgtWidth": 76.0, "TgtHeight": 110.0}, {"OwnSpeed": 83.7, "StrDeg": -0.9, "inf_DP": 5.769531, "Distance_ref": 54.18, "TgtSpeed_ref": 75.94, "TgtXPos_LeftUp": 447.0, "TgtYPos_LeftUp": 39.0, "TgtWidth": 77.0, "TgtHeight": 111.0}, {"OwnSpeed": 83.7, "StrDeg": -0.9, "inf_DP": 5.769531, "Distance_ref": 53.95, "TgtSpeed_ref": 75.9, "TgtXPos_LeftUp": 446.0, "TgtYPos_LeftUp": 40.0, "TgtWidth": 78.0, "TgtHeight": 111.0}, {"OwnSpeed": 83.5, "StrDeg": -0.9, "inf_DP": 5.769531, "Distance_ref": 53.75, "TgtSpeed_ref": 75.82, "TgtXPos_LeftUp": 446.0, "TgtYPos_LeftUp": 38.0, "TgtWidth": 78.0, "TgtHeight": 112.0}, {"OwnSpeed": 83.3, "StrDeg": -0.9, "inf_DP": 5.769531, "Distance_ref": 53.56, "TgtSpeed_ref": 75.78, "TgtXPos_LeftUp": 446.0, "TgtYPos_LeftUp": 36.0, "TgtWidth": 78.0, "TgtHeight": 112.0}, {"OwnSpeed": 83.2, "StrDeg": -0.9, "inf_DP": 5.769531, "Distance_ref": 53.35, "TgtSpeed_ref": 75.84, "TgtXPos_LeftUp": 446.0, "TgtYPos_LeftUp": 34.0, "TgtWidth": 79.0, "TgtHeight": 113.0}, {"OwnSpeed": 83.2, "StrDeg": -0.9, "inf_DP": 5.769531, "Distance_ref": 53.14, "TgtSpeed_ref": 75.84, "TgtXPos_LeftUp": 446.0, "TgtYPos_LeftUp": 36.0, "TgtWidth": 79.0, "TgtHeight": 112.0}, {"OwnSpeed": 83.0, "StrDeg": -0.8, "inf_DP": 5.769531, "Distance_ref": 52.95, "TgtSpeed_ref": 75.84, "TgtXPos_LeftUp": 446.0, "TgtYPos_LeftUp": 35.0, "TgtWidth": 80.0, "TgtHeight": 113.0}, {"OwnSpeed": 83.0, "StrDeg": -0.7, "inf_DP": 5.769531, "Distance_ref": 52.76, "TgtSpeed_ref": 75.88, "TgtXPos_LeftUp": 447.0, "TgtYPos_LeftUp": 36.0, "TgtWidth": 79.0, "TgtHeight": 113.0}, {"OwnSpeed": 82.8, "StrDeg": -0.7, "inf_DP": 5.769531, "Distance_ref": 52.58, "TgtSpeed_ref": 75.87, "TgtXPos_LeftUp": 447.0, "TgtYPos_LeftUp": 35.0, "TgtWidth": 80.0, "TgtHeight": 114.0}, {"OwnSpeed": 82.7, "StrDeg": -0.6, "inf_DP": 5.769531, "Distance_ref": 52.38, "TgtSpeed_ref": 75.92, "TgtXPos_LeftUp": 447.0, "TgtYPos_LeftUp": 33.0, "TgtWidth": 80.0, "TgtHeight": 115.0}, {"OwnSpeed": 82.6, "StrDeg": -0.7, "inf_DP": 5.769531, "Distance_ref": 52.16, "TgtSpeed_ref": 75.91, "TgtXPos_LeftUp": 447.0, "TgtYPos_LeftUp": 30.0, "TgtWidth": 80.0, "TgtHeight": 116.0}, {"OwnSpeed": 82.4, "StrDeg": -0.7, "inf_DP": 5.769531, "Distance_ref": 51.99, "TgtSpeed_ref": 75.84, "TgtXPos_LeftUp": 447.0, "TgtYPos_LeftUp": 29.0, "TgtWidth": 81.0, "TgtHeight": 116.0}, {"OwnSpeed": 82.4, "StrDeg": -0.6, "inf_DP": 5.769531, "Distance_ref": 51.82, "TgtSpeed_ref": 75.82, "TgtXPos_LeftUp": 448.0, "TgtYPos_LeftUp": 29.0, "TgtWidth": 81.0, "TgtHeight": 118.0}, {"OwnSpeed": 82.3, "StrDeg": -0.4, "inf_DP": 5.769531, "Distance_ref": 51.65, "TgtSpeed_ref": 75.85, "TgtXPos_LeftUp": 447.0, "TgtYPos_LeftUp": 33.0, "TgtWidth": 82.0, "TgtHeight": 119.0}, {"OwnSpeed": 82.3, "StrDeg": -0.3, "inf_DP": 5.769531, "Distance_ref": 51.46, "TgtSpeed_ref": 75.82, "TgtXPos_LeftUp": 448.0, "TgtYPos_LeftUp": 36.0, "TgtWidth": 81.0, "TgtHeight": 119.0}, {"OwnSpeed": 82.1, "StrDeg": -0.2, "inf_DP": 5.769531, "Distance_ref": 51.28, "TgtSpeed_ref": 75.81, "TgtXPos_LeftUp": 448.0, "TgtYPos_LeftUp": 36.0, "TgtWidth": 81.0, "TgtHeight": 119.0}, {"OwnSpeed": 81.9, "StrDeg": 0.0, "inf_DP": 5.769531, "Distance_ref": 51.12, "TgtSpeed_ref": 75.78, "TgtXPos_LeftUp": 447.0, "TgtYPos_LeftUp": 32.0, "TgtWidth": 82.0, "TgtHeight": 120.0}, {"OwnSpeed": 81.8, "StrDeg": 0.1, "inf_DP": 5.769531, "Distance_ref": 50.96, "TgtSpeed_ref": 75.81, "TgtXPos_LeftUp": 447.0, "TgtYPos_LeftUp": 31.0, "TgtWidth": 82.0, "TgtHeight": 120.0}, {"OwnSpeed": 81.6, "StrDeg": 0.2, "inf_DP": 5.769531, "Distance_ref": 50.79, "TgtSpeed_ref": 75.91, "TgtXPos_LeftUp": 447.0, "TgtYPos_LeftUp": 23.0, "TgtWidth": 82.0, "TgtHeight": 120.0}, {"OwnSpeed": 81.5, "StrDeg": 0.2, "inf_DP": 5.769531, "Distance_ref": 50.62, "TgtSpeed_ref": 75.91, "TgtXPos_LeftUp": 446.0, "TgtYPos_LeftUp": 20.0, "TgtWidth": 82.0, "TgtHeight": 121.0}, {"OwnSpeed": 81.5, "StrDeg": 0.2, "inf_DP": 5.769531, "Distance_ref": 50.46, "TgtSpeed_ref": 75.88, "TgtXPos_LeftUp": 445.0, "TgtYPos_LeftUp": 24.0, "TgtWidth": 83.0, "TgtHeight": 122.0}, {"OwnSpeed": 81.5, "StrDeg": 0.2, "inf_DP": 5.769531, "Distance_ref": 50.31, "TgtSpeed_ref": 75.87, "TgtXPos_LeftUp": 444.0, "TgtYPos_LeftUp": 30.0, "TgtWidth": 83.0, "TgtHeight": 122.0}, {"OwnSpeed": 81.4, "StrDeg": 0.2, "inf_DP": 5.769531, "Distance_ref": 50.16, "TgtSpeed_ref": 75.9, "TgtXPos_LeftUp": 444.0, "TgtYPos_LeftUp": 32.0, "TgtWidth": 83.0, "TgtHeight": 122.0}, {"OwnSpeed": 81.2, "StrDeg": 0.2, "inf_DP": 5.769531, "Distance_ref": 50.01, "TgtSpeed_ref": 75.97, "TgtXPos_LeftUp": 443.0, "TgtYPos_LeftUp": 26.0, "TgtWidth": 84.0, "TgtHeight": 123.0}, {"OwnSpeed": 81.1, "StrDeg": 0.2, "inf_DP": 5.769531, "Distance_ref": 49.86, "TgtSpeed_ref": 75.97, "TgtXPos_LeftUp": 442.0, "TgtYPos_LeftUp": 24.0, "TgtWidth": 84.0, "TgtHeight": 124.0}, {"OwnSpeed": 81.1, "StrDeg": 0.2, "inf_DP": 5.769531, "Distance_ref": 49.74, "TgtSpeed_ref": 75.95, "TgtXPos_LeftUp": 442.0, "TgtYPos_LeftUp": 28.0, "TgtWidth": 84.0, "TgtHeight": 124.0}, {"OwnSpeed": 80.9, "StrDeg": 0.2, "inf_DP": 5.769531, "Distance_ref": 49.61, "TgtSpeed_ref": 75.96, "TgtXPos_LeftUp": 442.0, "TgtYPos_LeftUp": 30.0, "TgtWidth": 84.0, "TgtHeight": 124.0}, {"OwnSpeed": 80.8, "StrDeg": 0.2, "inf_DP": 5.769531, "Distance_ref": 49.46, "TgtSpeed_ref": 76.02, "TgtXPos_LeftUp": 441.0, "TgtYPos_LeftUp": 27.0, "TgtWidth": 85.0, "TgtHeight": 125.0}, {"OwnSpeed": 80.7, "StrDeg": 0.2, "inf_DP": 5.769531, "Distance_ref": 49.34, "TgtSpeed_ref": 76.05, "TgtXPos_LeftUp": 441.0, "TgtYPos_LeftUp": 27.0, "TgtWidth": 85.0, "TgtHeight": 125.0}, {"OwnSpeed": 80.6, "StrDeg": 0.2, "inf_DP": 5.769531, "Distance_ref": 49.21, "TgtSpeed_ref": 76.07, "TgtXPos_LeftUp": 441.0, "TgtYPos_LeftUp": 30.0, "TgtWidth": 85.0, "TgtHeight": 125.0}, {"OwnSpeed": 80.6, "StrDeg": 0.2, "inf_DP": 5.769531, "Distance_ref": 49.09, "TgtSpeed_ref": 76.06, "TgtXPos_LeftUp": 441.0, "TgtYPos_LeftUp": 33.0, "TgtWidth": 84.0, "TgtHeight": 125.0}, {"OwnSpeed": 80.4, "StrDeg": 0.2, "inf_DP": 5.769531, "Distance_ref": 48.98, "TgtSpeed_ref": 76.09, "TgtXPos_LeftUp": 441.0, "TgtYPos_LeftUp": 34.0, "TgtWidth": 85.0, "TgtHeight": 125.0}, {"OwnSpeed": 80.4, "StrDeg": 0.2, "inf_DP": 5.769531, "Distance_ref": 48.85, "TgtSpeed_ref": 76.12, "TgtXPos_LeftUp": 440.0, "TgtYPos_LeftUp": 38.0, "TgtWidth": 85.0, "TgtHeight": 126.0}, {"OwnSpeed": 80.2, "StrDeg": 0.2, "inf_DP": 5.769531, "Distance_ref": 48.72, "TgtSpeed_ref": 76.11, "TgtXPos_LeftUp": 440.0, "TgtYPos_LeftUp": 36.0, "TgtWidth": 85.0, "TgtHeight": 127.0}, {"OwnSpeed": 79.9, "StrDeg": 0.2, "inf_DP": 5.769531, "Distance_ref": 48.62, "TgtSpeed_ref": 76.08, "TgtXPos_LeftUp": 440.0, "TgtYPos_LeftUp": 30.0, "TgtWidth": 86.0, "TgtHeight": 126.0}, {"OwnSpeed": 79.9, "StrDeg": 0.2, "inf_DP": 5.769531, "Distance_ref": 48.52, "TgtSpeed_ref": 76.06, "TgtXPos_LeftUp": 439.0, "TgtYPos_LeftUp": 30.0, "TgtWidth": 87.0, "TgtHeight": 126.0}, {"OwnSpeed": 79.8, "StrDeg": 0.2, "inf_DP": 5.769531, "Distance_ref": 48.42, "TgtSpeed_ref": 76.01, "TgtXPos_LeftUp": 440.0, "TgtYPos_LeftUp": 33.0, "TgtWidth": 86.0, "TgtHeight": 127.0}]}