{"attributes": {"評価値計算時の重み付加": "有"}, "sequence": [{"OwnSpeed": 40.8, "StrDeg": -2.7, "inf_DP": 5.755615, "Distance_ref": 18.29, "TgtSpeed_ref": 46.23, "TgtXPos_LeftUp": 396.0, "TgtYPos_LeftUp": 107.0, "TgtWidth": 147.0, "TgtHeight": 128.0}, {"OwnSpeed": 41.2, "StrDeg": -4.0, "inf_DP": 5.755615, "Distance_ref": 18.42, "TgtSpeed_ref": 46.32, "TgtXPos_LeftUp": 396.0, "TgtYPos_LeftUp": 108.0, "TgtWidth": 147.0, "TgtHeight": 129.0}, {"OwnSpeed": 41.6, "StrDeg": -5.4, "inf_DP": 5.755615, "Distance_ref": 18.55, "TgtSpeed_ref": 46.45, "TgtXPos_LeftUp": 398.0, "TgtYPos_LeftUp": 110.0, "TgtWidth": 146.0, "TgtHeight": 128.0}, {"OwnSpeed": 42.0, "StrDeg": -5.5, "inf_DP": 5.755615, "Distance_ref": 18.68, "TgtSpeed_ref": 46.56, "TgtXPos_LeftUp": 401.0, "TgtYPos_LeftUp": 110.0, "TgtWidth": 145.0, "TgtHeight": 127.0}, {"OwnSpeed": 42.3, "StrDeg": -5.5, "inf_DP": 5.755615, "Distance_ref": 18.79, "TgtSpeed_ref": 46.69, "TgtXPos_LeftUp": 404.0, "TgtYPos_LeftUp": 110.0, "TgtWidth": 144.0, "TgtHeight": 125.0}, {"OwnSpeed": 42.6, "StrDeg": -5.5, "inf_DP": 5.755615, "Distance_ref": 18.91, "TgtSpeed_ref": 46.84, "TgtXPos_LeftUp": 408.0, "TgtYPos_LeftUp": 108.0, "TgtWidth": 142.0, "TgtHeight": 125.0}, {"OwnSpeed": 42.9, "StrDeg": -5.5, "inf_DP": 5.755615, "Distance_ref": 19.01, "TgtSpeed_ref": 47.04, "TgtXPos_LeftUp": 411.0, "TgtYPos_LeftUp": 107.0, "TgtWidth": 141.0, "TgtHeight": 125.0}, {"OwnSpeed": 43.2, "StrDeg": -5.5, "inf_DP": 5.755615, "Distance_ref": 19.12, "TgtSpeed_ref": 47.22, "TgtXPos_LeftUp": 414.0, "TgtYPos_LeftUp": 103.0, "TgtWidth": 141.0, "TgtHeight": 125.0}, {"OwnSpeed": 43.4, "StrDeg": -5.5, "inf_DP": 5.755615, "Distance_ref": 19.24, "TgtSpeed_ref": 47.47, "TgtXPos_LeftUp": 418.0, "TgtYPos_LeftUp": 102.0, "TgtWidth": 139.0, "TgtHeight": 124.0}, {"OwnSpeed": 43.7, "StrDeg": -5.4, "inf_DP": 5.755615, "Distance_ref": 19.34, "TgtSpeed_ref": 47.77, "TgtXPos_LeftUp": 421.0, "TgtYPos_LeftUp": 103.0, "TgtWidth": 139.0, "TgtHeight": 122.0}, {"OwnSpeed": 43.9, "StrDeg": -5.1, "inf_DP": 5.755615, "Distance_ref": 19.44, "TgtSpeed_ref": 48.06, "TgtXPos_LeftUp": 424.0, "TgtYPos_LeftUp": 103.0, "TgtWidth": 138.0, "TgtHeight": 122.0}, {"OwnSpeed": 44.2, "StrDeg": -4.6, "inf_DP": 5.755615, "Distance_ref": 19.55, "TgtSpeed_ref": 48.3, "TgtXPos_LeftUp": 427.0, "TgtYPos_LeftUp": 104.0, "TgtWidth": 137.0, "TgtHeight": 122.0}, {"OwnSpeed": 44.4, "StrDeg": -3.5, "inf_DP": 5.755615, "Distance_ref": 19.66, "TgtSpeed_ref": 48.57, "TgtXPos_LeftUp": 430.0, "TgtYPos_LeftUp": 105.0, "TgtWidth": 135.0, "TgtHeight": 119.0}, {"OwnSpeed": 44.6, "StrDeg": -2.1, "inf_DP": 5.755615, "Distance_ref": 19.79, "TgtSpeed_ref": 48.83, "TgtXPos_LeftUp": 432.0, "TgtYPos_LeftUp": 104.0, "TgtWidth": 134.0, "TgtHeight": 121.0}, {"OwnSpeed": 44.8, "StrDeg": -1.2, "inf_DP": 5.755615, "Distance_ref": 19.91, "TgtSpeed_ref": 49.16, "TgtXPos_LeftUp": 432.0, "TgtYPos_LeftUp": 104.0, "TgtWidth": 134.0, "TgtHeight": 121.0}, {"OwnSpeed": 45.0, "StrDeg": -0.5, "inf_DP": 5.755615, "Distance_ref": 20.02, "TgtSpeed_ref": 49.44, "TgtXPos_LeftUp": 432.0, "TgtYPos_LeftUp": 104.0, "TgtWidth": 133.0, "TgtHeight": 121.0}, {"OwnSpeed": 45.2, "StrDeg": -0.1, "inf_DP": 5.755615, "Distance_ref": 20.16, "TgtSpeed_ref": 49.68, "TgtXPos_LeftUp": 432.0, "TgtYPos_LeftUp": 104.0, "TgtWidth": 132.0, "TgtHeight": 118.0}, {"OwnSpeed": 45.5, "StrDeg": 0.0, "inf_DP": 5.755615, "Distance_ref": 20.31, "TgtSpeed_ref": 49.96, "TgtXPos_LeftUp": 432.0, "TgtYPos_LeftUp": 104.0, "TgtWidth": 130.0, "TgtHeight": 119.0}, {"OwnSpeed": 45.6, "StrDeg": 0.0, "inf_DP": 5.755615, "Distance_ref": 20.44, "TgtSpeed_ref": 50.27, "TgtXPos_LeftUp": 430.0, "TgtYPos_LeftUp": 105.0, "TgtWidth": 131.0, "TgtHeight": 121.0}, {"OwnSpeed": 45.8, "StrDeg": -0.3, "inf_DP": 5.755615, "Distance_ref": 20.56, "TgtSpeed_ref": 50.5, "TgtXPos_LeftUp": 430.0, "TgtYPos_LeftUp": 105.0, "TgtWidth": 130.0, "TgtHeight": 122.0}, {"OwnSpeed": 46.0, "StrDeg": -2.4, "inf_DP": 5.755615, "Distance_ref": 20.69, "TgtSpeed_ref": 50.73, "TgtXPos_LeftUp": 430.0, "TgtYPos_LeftUp": 106.0, "TgtWidth": 129.0, "TgtHeight": 121.0}, {"OwnSpeed": 46.2, "StrDeg": -2.5, "inf_DP": 5.755615, "Distance_ref": 20.84, "TgtSpeed_ref": 50.85, "TgtXPos_LeftUp": 431.0, "TgtYPos_LeftUp": 106.0, "TgtWidth": 127.0, "TgtHeight": 120.0}, {"OwnSpeed": 46.4, "StrDeg": -2.9, "inf_DP": 5.755615, "Distance_ref": 20.98, "TgtSpeed_ref": 51.0, "TgtXPos_LeftUp": 432.0, "TgtYPos_LeftUp": 104.0, "TgtWidth": 126.0, "TgtHeight": 120.0}, {"OwnSpeed": 46.6, "StrDeg": -3.0, "inf_DP": 5.755615, "Distance_ref": 21.11, "TgtSpeed_ref": 51.16, "TgtXPos_LeftUp": 433.0, "TgtYPos_LeftUp": 104.0, "TgtWidth": 125.0, "TgtHeight": 119.0}, {"OwnSpeed": 46.8, "StrDeg": -3.0, "inf_DP": 5.755615, "Distance_ref": 21.24, "TgtSpeed_ref": 51.25, "TgtXPos_LeftUp": 435.0, "TgtYPos_LeftUp": 109.0, "TgtWidth": 123.0, "TgtHeight": 116.0}, {"OwnSpeed": 47.0, "StrDeg": -3.0, "inf_DP": 5.755615, "Distance_ref": 21.38, "TgtSpeed_ref": 51.28, "TgtXPos_LeftUp": 436.0, "TgtYPos_LeftUp": 109.0, "TgtWidth": 123.0, "TgtHeight": 115.0}, {"OwnSpeed": 47.2, "StrDeg": -2.9, "inf_DP": 5.755615, "Distance_ref": 21.51, "TgtSpeed_ref": 51.36, "TgtXPos_LeftUp": 437.0, "TgtYPos_LeftUp": 109.0, "TgtWidth": 123.0, "TgtHeight": 115.0}, {"OwnSpeed": 47.3, "StrDeg": -2.5, "inf_DP": 5.755615, "Distance_ref": 21.64, "TgtSpeed_ref": 51.43, "TgtXPos_LeftUp": 438.0, "TgtYPos_LeftUp": 106.0, "TgtWidth": 123.0, "TgtHeight": 114.0}, {"OwnSpeed": 47.4, "StrDeg": -2.5, "inf_DP": 5.755615, "Distance_ref": 21.74, "TgtSpeed_ref": 51.54, "TgtXPos_LeftUp": 438.0, "TgtYPos_LeftUp": 105.0, "TgtWidth": 123.0, "TgtHeight": 113.0}, {"OwnSpeed": 47.5, "StrDeg": -2.4, "inf_DP": 5.755615, "Distance_ref": 21.84, "TgtSpeed_ref": 51.58, "TgtXPos_LeftUp": 439.0, "TgtYPos_LeftUp": 105.0, "TgtWidth": 123.0, "TgtHeight": 113.0}, {"OwnSpeed": 47.5, "StrDeg": -2.3, "inf_DP": 5.755615, "Distance_ref": 21.95, "TgtSpeed_ref": 51.52, "TgtXPos_LeftUp": 440.0, "TgtYPos_LeftUp": 105.0, "TgtWidth": 123.0, "TgtHeight": 111.0}, {"OwnSpeed": 47.5, "StrDeg": -2.2, "inf_DP": 5.755615, "Distance_ref": 22.06, "TgtSpeed_ref": 51.48, "TgtXPos_LeftUp": 442.0, "TgtYPos_LeftUp": 102.0, "TgtWidth": 120.0, "TgtHeight": 111.0}, {"OwnSpeed": 47.5, "StrDeg": -1.8, "inf_DP": 5.755615, "Distance_ref": 22.16, "TgtSpeed_ref": 51.38, "TgtXPos_LeftUp": 443.0, "TgtYPos_LeftUp": 101.0, "TgtWidth": 118.0, "TgtHeight": 108.0}, {"OwnSpeed": 47.4, "StrDeg": -1.6, "inf_DP": 5.755615, "Distance_ref": 22.28, "TgtSpeed_ref": 51.2, "TgtXPos_LeftUp": 445.0, "TgtYPos_LeftUp": 102.0, "TgtWidth": 118.0, "TgtHeight": 108.0}, {"OwnSpeed": 47.3, "StrDeg": -1.4, "inf_DP": 5.755615, "Distance_ref": 22.39, "TgtSpeed_ref": 50.99, "TgtXPos_LeftUp": 446.0, "TgtYPos_LeftUp": 101.0, "TgtWidth": 117.0, "TgtHeight": 109.0}, {"OwnSpeed": 47.2, "StrDeg": -1.0, "inf_DP": 5.755615, "Distance_ref": 22.54, "TgtSpeed_ref": 50.7, "TgtXPos_LeftUp": 447.0, "TgtYPos_LeftUp": 99.0, "TgtWidth": 116.0, "TgtHeight": 109.0}, {"OwnSpeed": 47.2, "StrDeg": -0.8, "inf_DP": 5.755615, "Distance_ref": 22.66, "TgtSpeed_ref": 50.44, "TgtXPos_LeftUp": 448.0, "TgtYPos_LeftUp": 100.0, "TgtWidth": 116.0, "TgtHeight": 108.0}, {"OwnSpeed": 47.1, "StrDeg": -0.5, "inf_DP": 5.755615, "Distance_ref": 22.76, "TgtSpeed_ref": 50.11, "TgtXPos_LeftUp": 448.0, "TgtYPos_LeftUp": 102.0, "TgtWidth": 116.0, "TgtHeight": 108.0}, {"OwnSpeed": 47.0, "StrDeg": 0.0, "inf_DP": 5.755615, "Distance_ref": 22.86, "TgtSpeed_ref": 49.68, "TgtXPos_LeftUp": 449.0, "TgtYPos_LeftUp": 104.0, "TgtWidth": 115.0, "TgtHeight": 107.0}, {"OwnSpeed": 46.9, "StrDeg": 0.3, "inf_DP": 5.755615, "Distance_ref": 22.95, "TgtSpeed_ref": 49.23, "TgtXPos_LeftUp": 450.0, "TgtYPos_LeftUp": 104.0, "TgtWidth": 113.0, "TgtHeight": 106.0}, {"OwnSpeed": 46.8, "StrDeg": 0.4, "inf_DP": 5.755615, "Distance_ref": 23.02, "TgtSpeed_ref": 48.78, "TgtXPos_LeftUp": 450.0, "TgtYPos_LeftUp": 103.0, "TgtWidth": 113.0, "TgtHeight": 106.0}, {"OwnSpeed": 46.7, "StrDeg": 0.6, "inf_DP": 5.755615, "Distance_ref": 23.08, "TgtSpeed_ref": 48.28, "TgtXPos_LeftUp": 450.0, "TgtYPos_LeftUp": 105.0, "TgtWidth": 112.0, "TgtHeight": 105.0}, {"OwnSpeed": 46.6, "StrDeg": 0.7, "inf_DP": 5.755615, "Distance_ref": 23.11, "TgtSpeed_ref": 47.65, "TgtXPos_LeftUp": 450.0, "TgtYPos_LeftUp": 108.0, "TgtWidth": 112.0, "TgtHeight": 106.0}, {"OwnSpeed": 46.4, "StrDeg": 0.7, "inf_DP": 5.755615, "Distance_ref": 23.13, "TgtSpeed_ref": 46.93, "TgtXPos_LeftUp": 450.0, "TgtYPos_LeftUp": 107.0, "TgtWidth": 113.0, "TgtHeight": 105.0}, {"OwnSpeed": 46.3, "StrDeg": 0.7, "inf_DP": 5.755615, "Distance_ref": 23.12, "TgtSpeed_ref": 46.24, "TgtXPos_LeftUp": 449.0, "TgtYPos_LeftUp": 105.0, "TgtWidth": 114.0, "TgtHeight": 105.0}, {"OwnSpeed": 46.2, "StrDeg": 0.7, "inf_DP": 5.755615, "Distance_ref": 23.09, "TgtSpeed_ref": 45.63, "TgtXPos_LeftUp": 448.0, "TgtYPos_LeftUp": 104.0, "TgtWidth": 112.0, "TgtHeight": 106.0}, {"OwnSpeed": 46.2, "StrDeg": 0.9, "inf_DP": 5.755615, "Distance_ref": 23.05, "TgtSpeed_ref": 45.02, "TgtXPos_LeftUp": 448.0, "TgtYPos_LeftUp": 106.0, "TgtWidth": 112.0, "TgtHeight": 105.0}, {"OwnSpeed": 46.1, "StrDeg": 1.4, "inf_DP": 5.755615, "Distance_ref": 23.01, "TgtSpeed_ref": 44.43, "TgtXPos_LeftUp": 447.0, "TgtYPos_LeftUp": 103.0, "TgtWidth": 114.0, "TgtHeight": 106.0}, {"OwnSpeed": 46.1, "StrDeg": 2.1, "inf_DP": 5.755615, "Distance_ref": 22.95, "TgtSpeed_ref": 43.89, "TgtXPos_LeftUp": 446.0, "TgtYPos_LeftUp": 101.0, "TgtWidth": 114.0, "TgtHeight": 105.0}, {"OwnSpeed": 46.0, "StrDeg": 2.6, "inf_DP": 5.755615, "Distance_ref": 22.84, "TgtSpeed_ref": 43.49, "TgtXPos_LeftUp": 444.0, "TgtYPos_LeftUp": 97.0, "TgtWidth": 114.0, "TgtHeight": 107.0}, {"OwnSpeed": 45.9, "StrDeg": 2.7, "inf_DP": 5.755615, "Distance_ref": 22.72, "TgtSpeed_ref": 43.16, "TgtXPos_LeftUp": 441.0, "TgtYPos_LeftUp": 96.0, "TgtWidth": 116.0, "TgtHeight": 107.0}, {"OwnSpeed": 45.8, "StrDeg": 2.7, "inf_DP": 5.755615, "Distance_ref": 22.59, "TgtSpeed_ref": 42.85, "TgtXPos_LeftUp": 439.0, "TgtYPos_LeftUp": 95.0, "TgtWidth": 116.0, "TgtHeight": 108.0}, {"OwnSpeed": 45.7, "StrDeg": 2.7, "inf_DP": 5.755615, "Distance_ref": 22.48, "TgtSpeed_ref": 42.57, "TgtXPos_LeftUp": 436.0, "TgtYPos_LeftUp": 98.0, "TgtWidth": 116.0, "TgtHeight": 108.0}, {"OwnSpeed": 45.7, "StrDeg": 2.7, "inf_DP": 5.755615, "Distance_ref": 22.36, "TgtSpeed_ref": 42.35, "TgtXPos_LeftUp": 434.0, "TgtYPos_LeftUp": 103.0, "TgtWidth": 116.0, "TgtHeight": 108.0}, {"OwnSpeed": 45.6, "StrDeg": 2.7, "inf_DP": 5.755615, "Distance_ref": 22.24, "TgtSpeed_ref": 42.14, "TgtXPos_LeftUp": 431.0, "TgtYPos_LeftUp": 104.0, "TgtWidth": 117.0, "TgtHeight": 108.0}, {"OwnSpeed": 45.5, "StrDeg": 2.1, "inf_DP": 5.755615, "Distance_ref": 22.12, "TgtSpeed_ref": 41.92, "TgtXPos_LeftUp": 429.0, "TgtYPos_LeftUp": 104.0, "TgtWidth": 118.0, "TgtHeight": 108.0}, {"OwnSpeed": 45.3, "StrDeg": 1.8, "inf_DP": 5.755615, "Distance_ref": 22.05, "TgtSpeed_ref": 41.69, "TgtXPos_LeftUp": 427.0, "TgtYPos_LeftUp": 105.0, "TgtWidth": 118.0, "TgtHeight": 109.0}, {"OwnSpeed": 45.2, "StrDeg": 1.6, "inf_DP": 5.755615, "Distance_ref": 21.98, "TgtSpeed_ref": 41.61, "TgtXPos_LeftUp": 424.0, "TgtYPos_LeftUp": 104.0, "TgtWidth": 120.0, "TgtHeight": 110.0}, {"OwnSpeed": 45.1, "StrDeg": 0.9, "inf_DP": 5.755615, "Distance_ref": 21.91, "TgtSpeed_ref": 41.55, "TgtXPos_LeftUp": 424.0, "TgtYPos_LeftUp": 102.0, "TgtWidth": 119.0, "TgtHeight": 111.0}, {"OwnSpeed": 45.0, "StrDeg": 0.1, "inf_DP": 5.755615, "Distance_ref": 21.82, "TgtSpeed_ref": 41.51, "TgtXPos_LeftUp": 422.0, "TgtYPos_LeftUp": 100.0, "TgtWidth": 120.0, "TgtHeight": 113.0}, {"OwnSpeed": 44.9, "StrDeg": -0.3, "inf_DP": 5.755615, "Distance_ref": 21.74, "TgtSpeed_ref": 41.44, "TgtXPos_LeftUp": 421.0, "TgtYPos_LeftUp": 100.0, "TgtWidth": 121.0, "TgtHeight": 112.0}, {"OwnSpeed": 44.8, "StrDeg": -0.2, "inf_DP": 5.755615, "Distance_ref": 21.65, "TgtSpeed_ref": 41.3, "TgtXPos_LeftUp": 420.0, "TgtYPos_LeftUp": 100.0, "TgtWidth": 122.0, "TgtHeight": 114.0}, {"OwnSpeed": 44.7, "StrDeg": -0.2, "inf_DP": 5.755615, "Distance_ref": 21.55, "TgtSpeed_ref": 41.17, "TgtXPos_LeftUp": 419.0, "TgtYPos_LeftUp": 102.0, "TgtWidth": 123.0, "TgtHeight": 114.0}, {"OwnSpeed": 44.6, "StrDeg": -0.2, "inf_DP": 5.755615, "Distance_ref": 21.44, "TgtSpeed_ref": 41.05, "TgtXPos_LeftUp": 418.0, "TgtYPos_LeftUp": 101.0, "TgtWidth": 123.0, "TgtHeight": 116.0}, {"OwnSpeed": 44.4, "StrDeg": -0.2, "inf_DP": 5.755615, "Distance_ref": 21.34, "TgtSpeed_ref": 40.79, "TgtXPos_LeftUp": 418.0, "TgtYPos_LeftUp": 97.0, "TgtWidth": 123.0, "TgtHeight": 115.0}, {"OwnSpeed": 44.3, "StrDeg": -0.3, "inf_DP": 5.755615, "Distance_ref": 21.24, "TgtSpeed_ref": 40.49, "TgtXPos_LeftUp": 418.0, "TgtYPos_LeftUp": 94.0, "TgtWidth": 124.0, "TgtHeight": 117.0}, {"OwnSpeed": 44.3, "StrDeg": -0.5, "inf_DP": 5.755615, "Distance_ref": 21.14, "TgtSpeed_ref": 40.18, "TgtXPos_LeftUp": 417.0, "TgtYPos_LeftUp": 97.0, "TgtWidth": 124.0, "TgtHeight": 116.0}, {"OwnSpeed": 44.1, "StrDeg": -1.0, "inf_DP": 5.755615, "Distance_ref": 21.04, "TgtSpeed_ref": 39.91, "TgtXPos_LeftUp": 416.0, "TgtYPos_LeftUp": 98.0, "TgtWidth": 126.0, "TgtHeight": 118.0}, {"OwnSpeed": 44.0, "StrDeg": -0.9, "inf_DP": 5.755615, "Distance_ref": 20.91, "TgtSpeed_ref": 39.7, "TgtXPos_LeftUp": 415.0, "TgtYPos_LeftUp": 99.0, "TgtWidth": 127.0, "TgtHeight": 119.0}, {"OwnSpeed": 43.8, "StrDeg": -0.9, "inf_DP": 5.755615, "Distance_ref": 20.78, "TgtSpeed_ref": 39.45, "TgtXPos_LeftUp": 416.0, "TgtYPos_LeftUp": 102.0, "TgtWidth": 127.0, "TgtHeight": 120.0}, {"OwnSpeed": 43.7, "StrDeg": -0.9, "inf_DP": 5.755615, "Distance_ref": 20.66, "TgtSpeed_ref": 39.2, "TgtXPos_LeftUp": 415.0, "TgtYPos_LeftUp": 104.0, "TgtWidth": 128.0, "TgtHeight": 120.0}, {"OwnSpeed": 43.4, "StrDeg": -0.9, "inf_DP": 5.755615, "Distance_ref": 20.54, "TgtSpeed_ref": 39.18, "TgtXPos_LeftUp": 416.0, "TgtYPos_LeftUp": 103.0, "TgtWidth": 128.0, "TgtHeight": 121.0}, {"OwnSpeed": 43.3, "StrDeg": -1.0, "inf_DP": 5.755615, "Distance_ref": 20.39, "TgtSpeed_ref": 39.06, "TgtXPos_LeftUp": 415.0, "TgtYPos_LeftUp": 100.0, "TgtWidth": 130.0, "TgtHeight": 122.0}, {"OwnSpeed": 43.1, "StrDeg": -1.0, "inf_DP": 5.755615, "Distance_ref": 20.25, "TgtSpeed_ref": 38.86, "TgtXPos_LeftUp": 416.0, "TgtYPos_LeftUp": 99.0, "TgtWidth": 129.0, "TgtHeight": 123.0}, {"OwnSpeed": 42.9, "StrDeg": -0.9, "inf_DP": 5.755615, "Distance_ref": 20.11, "TgtSpeed_ref": 38.59, "TgtXPos_LeftUp": 415.0, "TgtYPos_LeftUp": 98.0, "TgtWidth": 131.0, "TgtHeight": 124.0}, {"OwnSpeed": 42.8, "StrDeg": -0.6, "inf_DP": 5.755615, "Distance_ref": 19.99, "TgtSpeed_ref": 38.28, "TgtXPos_LeftUp": 414.0, "TgtYPos_LeftUp": 98.0, "TgtWidth": 132.0, "TgtHeight": 124.0}, {"OwnSpeed": 42.6, "StrDeg": 0.0, "inf_DP": 5.755615, "Distance_ref": 19.86, "TgtSpeed_ref": 38.05, "TgtXPos_LeftUp": 413.0, "TgtYPos_LeftUp": 99.0, "TgtWidth": 134.0, "TgtHeight": 125.0}, {"OwnSpeed": 42.5, "StrDeg": 1.0, "inf_DP": 5.755615, "Distance_ref": 19.72, "TgtSpeed_ref": 37.86, "TgtXPos_LeftUp": 411.0, "TgtYPos_LeftUp": 102.0, "TgtWidth": 135.0, "TgtHeight": 125.0}, {"OwnSpeed": 42.3, "StrDeg": 1.3, "inf_DP": 5.755615, "Distance_ref": 19.66, "TgtSpeed_ref": 37.46, "TgtXPos_LeftUp": 409.0, "TgtYPos_LeftUp": 103.0, "TgtWidth": 136.0, "TgtHeight": 127.0}, {"OwnSpeed": 42.0, "StrDeg": 1.3, "inf_DP": 5.755615, "Distance_ref": 19.58, "TgtSpeed_ref": 37.2, "TgtXPos_LeftUp": 407.0, "TgtYPos_LeftUp": 99.0, "TgtWidth": 136.0, "TgtHeight": 128.0}, {"OwnSpeed": 41.9, "StrDeg": 1.3, "inf_DP": 5.755615, "Distance_ref": 19.46, "TgtSpeed_ref": 37.08, "TgtXPos_LeftUp": 404.0, "TgtYPos_LeftUp": 97.0, "TgtWidth": 137.0, "TgtHeight": 129.0}, {"OwnSpeed": 41.7, "StrDeg": 1.3, "inf_DP": 5.755615, "Distance_ref": 19.32, "TgtSpeed_ref": 37.07, "TgtXPos_LeftUp": 401.0, "TgtYPos_LeftUp": 99.0, "TgtWidth": 139.0, "TgtHeight": 131.0}, {"OwnSpeed": 41.5, "StrDeg": 1.3, "inf_DP": 5.755615, "Distance_ref": 19.16, "TgtSpeed_ref": 37.12, "TgtXPos_LeftUp": 398.0, "TgtYPos_LeftUp": 100.0, "TgtWidth": 140.0, "TgtHeight": 130.0}, {"OwnSpeed": 41.2, "StrDeg": 1.2, "inf_DP": 5.755615, "Distance_ref": 19.02, "TgtSpeed_ref": 37.1, "TgtXPos_LeftUp": 396.0, "TgtYPos_LeftUp": 100.0, "TgtWidth": 140.0, "TgtHeight": 131.0}, {"OwnSpeed": 40.9, "StrDeg": -0.1, "inf_DP": 5.755615, "Distance_ref": 18.89, "TgtSpeed_ref": 37.14, "TgtXPos_LeftUp": 393.0, "TgtYPos_LeftUp": 95.0, "TgtWidth": 142.0, "TgtHeight": 133.0}, {"OwnSpeed": 40.7, "StrDeg": -2.4, "inf_DP": 5.755615, "Distance_ref": 18.69, "TgtSpeed_ref": 37.23, "TgtXPos_LeftUp": 392.0, "TgtYPos_LeftUp": 92.0, "TgtWidth": 141.0, "TgtHeight": 134.0}, {"OwnSpeed": 40.6, "StrDeg": -3.5, "inf_DP": 5.755615, "Distance_ref": 18.54, "TgtSpeed_ref": 37.14, "TgtXPos_LeftUp": 390.0, "TgtYPos_LeftUp": 91.0, "TgtWidth": 144.0, "TgtHeight": 138.0}, {"OwnSpeed": 40.5, "StrDeg": -3.5, "inf_DP": 5.755615, "Distance_ref": 18.42, "TgtSpeed_ref": 37.13, "TgtXPos_LeftUp": 390.0, "TgtYPos_LeftUp": 101.0, "TgtWidth": 144.0, "TgtHeight": 134.0}, {"OwnSpeed": 40.3, "StrDeg": -3.5, "inf_DP": 5.755615, "Distance_ref": 18.35, "TgtSpeed_ref": 37.19, "TgtXPos_LeftUp": 390.0, "TgtYPos_LeftUp": 103.0, "TgtWidth": 145.0, "TgtHeight": 135.0}, {"OwnSpeed": 40.1, "StrDeg": -3.9, "inf_DP": 5.755615, "Distance_ref": 18.31, "TgtSpeed_ref": 37.32, "TgtXPos_LeftUp": 390.0, "TgtYPos_LeftUp": 103.0, "TgtWidth": 145.0, "TgtHeight": 135.0}, {"OwnSpeed": 39.9, "StrDeg": -4.4, "inf_DP": 5.755615, "Distance_ref": 18.26, "TgtSpeed_ref": 37.52, "TgtXPos_LeftUp": 390.0, "TgtYPos_LeftUp": 101.0, "TgtWidth": 146.0, "TgtHeight": 135.0}, {"OwnSpeed": 39.7, "StrDeg": -4.9, "inf_DP": 5.755615, "Distance_ref": 18.24, "TgtSpeed_ref": 37.7, "TgtXPos_LeftUp": 391.0, "TgtYPos_LeftUp": 100.0, "TgtWidth": 147.0, "TgtHeight": 131.0}, {"OwnSpeed": 39.6, "StrDeg": -4.9, "inf_DP": 5.755615, "Distance_ref": 18.21, "TgtSpeed_ref": 37.87, "TgtXPos_LeftUp": 393.0, "TgtYPos_LeftUp": 102.0, "TgtWidth": 146.0, "TgtHeight": 134.0}, {"OwnSpeed": 39.5, "StrDeg": -4.9, "inf_DP": 5.755615, "Distance_ref": 18.19, "TgtSpeed_ref": 38.22, "TgtXPos_LeftUp": 395.0, "TgtYPos_LeftUp": 103.0, "TgtWidth": 146.0, "TgtHeight": 135.0}, {"OwnSpeed": 39.3, "StrDeg": -4.9, "inf_DP": 5.755615, "Distance_ref": 18.18, "TgtSpeed_ref": 38.5, "TgtXPos_LeftUp": 397.0, "TgtYPos_LeftUp": 103.0, "TgtWidth": 146.0, "TgtHeight": 133.0}, {"OwnSpeed": 39.2, "StrDeg": -4.9, "inf_DP": 5.755615, "Distance_ref": 18.16, "TgtSpeed_ref": 38.68, "TgtXPos_LeftUp": 399.0, "TgtYPos_LeftUp": 102.0, "TgtWidth": 146.0, "TgtHeight": 134.0}, {"OwnSpeed": 39.0, "StrDeg": -4.9, "inf_DP": 5.755615, "Distance_ref": 18.15, "TgtSpeed_ref": 38.78, "TgtXPos_LeftUp": 402.0, "TgtYPos_LeftUp": 101.0, "TgtWidth": 146.0, "TgtHeight": 133.0}, {"OwnSpeed": 38.8, "StrDeg": -4.8, "inf_DP": 5.755615, "Distance_ref": 18.15, "TgtSpeed_ref": 38.82, "TgtXPos_LeftUp": 404.0, "TgtYPos_LeftUp": 100.0, "TgtWidth": 146.0, "TgtHeight": 135.0}, {"OwnSpeed": 38.8, "StrDeg": -4.3, "inf_DP": 5.755615, "Distance_ref": 18.15, "TgtSpeed_ref": 38.88, "TgtXPos_LeftUp": 406.0, "TgtYPos_LeftUp": 102.0, "TgtWidth": 146.0, "TgtHeight": 136.0}, {"OwnSpeed": 38.8, "StrDeg": -3.5, "inf_DP": 5.755615, "Distance_ref": 18.15, "TgtSpeed_ref": 38.92, "TgtXPos_LeftUp": 408.0, "TgtYPos_LeftUp": 107.0, "TgtWidth": 146.0, "TgtHeight": 136.0}, {"OwnSpeed": 38.7, "StrDeg": -2.6, "inf_DP": 5.755615, "Distance_ref": 18.15, "TgtSpeed_ref": 38.97, "TgtXPos_LeftUp": 409.0, "TgtYPos_LeftUp": 108.0, "TgtWidth": 146.0, "TgtHeight": 136.0}, {"OwnSpeed": 38.7, "StrDeg": -1.8, "inf_DP": 5.755615, "Distance_ref": 18.16, "TgtSpeed_ref": 38.96, "TgtXPos_LeftUp": 410.0, "TgtYPos_LeftUp": 105.0, "TgtWidth": 146.0, "TgtHeight": 136.0}, {"OwnSpeed": 38.6, "StrDeg": -1.2, "inf_DP": 5.755615, "Distance_ref": 18.18, "TgtSpeed_ref": 38.96, "TgtXPos_LeftUp": 411.0, "TgtYPos_LeftUp": 101.0, "TgtWidth": 144.0, "TgtHeight": 132.0}, {"OwnSpeed": 38.6, "StrDeg": -1.0, "inf_DP": 5.755615, "Distance_ref": 18.19, "TgtSpeed_ref": 38.97, "TgtXPos_LeftUp": 412.0, "TgtYPos_LeftUp": 99.0, "TgtWidth": 144.0, "TgtHeight": 132.0}, {"OwnSpeed": 38.7, "StrDeg": -0.7, "inf_DP": 5.755615, "Distance_ref": 18.21, "TgtSpeed_ref": 38.97, "TgtXPos_LeftUp": 412.0, "TgtYPos_LeftUp": 100.0, "TgtWidth": 144.0, "TgtHeight": 132.0}, {"OwnSpeed": 38.7, "StrDeg": -0.4, "inf_DP": 5.755615, "Distance_ref": 18.22, "TgtSpeed_ref": 38.95, "TgtXPos_LeftUp": 412.0, "TgtYPos_LeftUp": 102.0, "TgtWidth": 144.0, "TgtHeight": 132.0}, {"OwnSpeed": 38.8, "StrDeg": 0.0, "inf_DP": 5.755615, "Distance_ref": 18.24, "TgtSpeed_ref": 38.93, "TgtXPos_LeftUp": 411.0, "TgtYPos_LeftUp": 104.0, "TgtWidth": 144.0, "TgtHeight": 131.0}, {"OwnSpeed": 38.8, "StrDeg": 0.3, "inf_DP": 5.755615, "Distance_ref": 18.25, "TgtSpeed_ref": 38.91, "TgtXPos_LeftUp": 410.0, "TgtYPos_LeftUp": 104.0, "TgtWidth": 145.0, "TgtHeight": 132.0}, {"OwnSpeed": 38.8, "StrDeg": 0.4, "inf_DP": 5.755615, "Distance_ref": 18.25, "TgtSpeed_ref": 38.9, "TgtXPos_LeftUp": 410.0, "TgtYPos_LeftUp": 101.0, "TgtWidth": 144.0, "TgtHeight": 135.0}, {"OwnSpeed": 38.8, "StrDeg": 0.6, "inf_DP": 5.755615, "Distance_ref": 18.25, "TgtSpeed_ref": 38.89, "TgtXPos_LeftUp": 408.0, "TgtYPos_LeftUp": 101.0, "TgtWidth": 144.0, "TgtHeight": 134.0}, {"OwnSpeed": 38.9, "StrDeg": 0.6, "inf_DP": 5.755615, "Distance_ref": 18.25, "TgtSpeed_ref": 38.89, "TgtXPos_LeftUp": 408.0, "TgtYPos_LeftUp": 102.0, "TgtWidth": 144.0, "TgtHeight": 133.0}, {"OwnSpeed": 39.0, "StrDeg": 0.6, "inf_DP": 5.755615, "Distance_ref": 18.24, "TgtSpeed_ref": 38.93, "TgtXPos_LeftUp": 406.0, "TgtYPos_LeftUp": 103.0, "TgtWidth": 144.0, "TgtHeight": 136.0}, {"OwnSpeed": 39.0, "StrDeg": 0.6, "inf_DP": 5.755615, "Distance_ref": 18.22, "TgtSpeed_ref": 38.99, "TgtXPos_LeftUp": 404.0, "TgtYPos_LeftUp": 104.0, "TgtWidth": 144.0, "TgtHeight": 136.0}, {"OwnSpeed": 39.0, "StrDeg": -0.8, "inf_DP": 5.755615, "Distance_ref": 18.21, "TgtSpeed_ref": 39.07, "TgtXPos_LeftUp": 404.0, "TgtYPos_LeftUp": 104.0, "TgtWidth": 144.0, "TgtHeight": 136.0}, {"OwnSpeed": 39.0, "StrDeg": -1.4, "inf_DP": 5.755615, "Distance_ref": 18.19, "TgtSpeed_ref": 39.14, "TgtXPos_LeftUp": 403.0, "TgtYPos_LeftUp": 102.0, "TgtWidth": 144.0, "TgtHeight": 136.0}, {"OwnSpeed": 39.0, "StrDeg": -1.5, "inf_DP": 5.755615, "Distance_ref": 18.18, "TgtSpeed_ref": 39.2, "TgtXPos_LeftUp": 402.0, "TgtYPos_LeftUp": 102.0, "TgtWidth": 145.0, "TgtHeight": 136.0}, {"OwnSpeed": 39.1, "StrDeg": -1.5, "inf_DP": 5.755615, "Distance_ref": 18.18, "TgtSpeed_ref": 39.31, "TgtXPos_LeftUp": 403.0, "TgtYPos_LeftUp": 102.0, "TgtWidth": 144.0, "TgtHeight": 136.0}, {"OwnSpeed": 39.1, "StrDeg": -1.5, "inf_DP": 5.755615, "Distance_ref": 18.18, "TgtSpeed_ref": 39.46, "TgtXPos_LeftUp": 403.0, "TgtYPos_LeftUp": 103.0, "TgtWidth": 144.0, "TgtHeight": 135.0}, {"OwnSpeed": 39.2, "StrDeg": -1.5, "inf_DP": 5.755615, "Distance_ref": 18.19, "TgtSpeed_ref": 39.63, "TgtXPos_LeftUp": 402.0, "TgtYPos_LeftUp": 104.0, "TgtWidth": 145.0, "TgtHeight": 136.0}, {"OwnSpeed": 39.2, "StrDeg": -1.5, "inf_DP": 5.755615, "Distance_ref": 18.22, "TgtSpeed_ref": 39.8, "TgtXPos_LeftUp": 403.0, "TgtYPos_LeftUp": 106.0, "TgtWidth": 145.0, "TgtHeight": 137.0}, {"OwnSpeed": 39.3, "StrDeg": -1.5, "inf_DP": 5.755615, "Distance_ref": 18.25, "TgtSpeed_ref": 40.01, "TgtXPos_LeftUp": 403.0, "TgtYPos_LeftUp": 107.0, "TgtWidth": 145.0, "TgtHeight": 137.0}, {"OwnSpeed": 39.3, "StrDeg": -1.5, "inf_DP": 5.755615, "Distance_ref": 18.28, "TgtSpeed_ref": 40.23, "TgtXPos_LeftUp": 404.0, "TgtYPos_LeftUp": 106.0, "TgtWidth": 144.0, "TgtHeight": 135.0}, {"OwnSpeed": 39.3, "StrDeg": -1.5, "inf_DP": 5.755615, "Distance_ref": 18.31, "TgtSpeed_ref": 40.51, "TgtXPos_LeftUp": 404.0, "TgtYPos_LeftUp": 102.0, "TgtWidth": 144.0, "TgtHeight": 135.0}, {"OwnSpeed": 39.3, "StrDeg": -1.5, "inf_DP": 5.755615, "Distance_ref": 18.34, "TgtSpeed_ref": 40.75, "TgtXPos_LeftUp": 404.0, "TgtYPos_LeftUp": 101.0, "TgtWidth": 144.0, "TgtHeight": 135.0}, {"OwnSpeed": 39.5, "StrDeg": -1.4, "inf_DP": 5.755615, "Distance_ref": 18.38, "TgtSpeed_ref": 40.96, "TgtXPos_LeftUp": 404.0, "TgtYPos_LeftUp": 102.0, "TgtWidth": 144.0, "TgtHeight": 136.0}, {"OwnSpeed": 39.5, "StrDeg": -1.4, "inf_DP": 5.755615, "Distance_ref": 18.44, "TgtSpeed_ref": 41.17, "TgtXPos_LeftUp": 405.0, "TgtYPos_LeftUp": 104.0, "TgtWidth": 143.0, "TgtHeight": 134.0}, {"OwnSpeed": 39.5, "StrDeg": -1.4, "inf_DP": 5.755615, "Distance_ref": 18.48, "TgtSpeed_ref": 41.37, "TgtXPos_LeftUp": 406.0, "TgtYPos_LeftUp": 106.0, "TgtWidth": 142.0, "TgtHeight": 135.0}, {"OwnSpeed": 39.6, "StrDeg": -1.4, "inf_DP": 5.755615, "Distance_ref": 18.54, "TgtSpeed_ref": 41.51, "TgtXPos_LeftUp": 406.0, "TgtYPos_LeftUp": 107.0, "TgtWidth": 142.0, "TgtHeight": 134.0}, {"OwnSpeed": 39.6, "StrDeg": -1.3, "inf_DP": 5.755615, "Distance_ref": 18.59, "TgtSpeed_ref": 41.71, "TgtXPos_LeftUp": 407.0, "TgtYPos_LeftUp": 105.0, "TgtWidth": 142.0, "TgtHeight": 133.0}, {"OwnSpeed": 39.6, "StrDeg": -1.1, "inf_DP": 5.755615, "Distance_ref": 18.68, "TgtSpeed_ref": 41.91, "TgtXPos_LeftUp": 407.0, "TgtYPos_LeftUp": 103.0, "TgtWidth": 141.0, "TgtHeight": 133.0}, {"OwnSpeed": 39.6, "StrDeg": -1.1, "inf_DP": 5.755615, "Distance_ref": 18.75, "TgtSpeed_ref": 42.12, "TgtXPos_LeftUp": 408.0, "TgtYPos_LeftUp": 103.0, "TgtWidth": 140.0, "TgtHeight": 131.0}]}